<?xml version="1.0" encoding="utf-8" standalone="yes" ?>
<T3locallangExt>
	<data type="array">
		<languageKey index="ch" type="array">
			<label index="statusEditingOn">编辑已打开</label>
			<label index="statusEditingOff">编辑已关闭</label>
			<label index="statusDeactivateEditing">关闭编辑</label>
			<label index="statusActivateEditing">激活编辑</label>
			<label index="closeEditMode">关闭编辑</label>
			<label index="openEditMode">编辑页面</label>
			<label index="toggle_advanced">高级</label>
			<label index="toggle_simple">简单</label>
			<label index="alertChange">这些改变将影响到表单中有效的字段，为了得到一个新的字段请保存当前内容.</label>
			<label index="fe_users.tx_wecfeedit_beuser">链接到后台用户</label>
			<label index="usersOnPage">警告：有用户正在编辑此页</label>
			<label index="copyIcon">拷贝</label>
			<label index="copyTitle">拷贝元素</label>
			<label index="cutIcon">剪切</label>
			<label index="cutTitle">剪切元素</label>
			<label index="deleteIcon">删除</label>
			<label index="deleteTitle">删除元素</label>
			<label index="downIcon">向下</label>
			<label index="downTitle">向下移动</label>
			<label index="editIcon">编辑</label>
			<label index="editTitle">点击编辑元素</label>
			<label index="hideIcon">隐藏</label>
			<label index="hideTitle">隐藏元素</label>
			<label index="newPageIcon">新页面</label>
			<label index="newRecordIcon">新建</label>
			<label index="newRecordInTopOfColumnTitle">在当前列顶部创建</label>
			<label index="newRecordTitle">在当前元素后新建</label>
			<label index="pasteIcon">粘贴</label>
			<label index="pasteTitle">在已存在元素后粘贴</label>
			<label index="refTitle">创建索引</label>
			<label index="unhideIcon">显示</label>
			<label index="unhideTitle">显示隐藏的元素</label>
			<label index="dragIcon">拖动</label>
			<label index="dragTitle">点击拖动元素</label>
			<label index="upIcon">向上</label>
			<label index="upTitle">向上移动</label>
			<label index="saveButton">保存</label>
			<label index="saveCloseButton">保存&amp;关闭</label>
			<label index="closeButton">关闭</label>
			<label index="pageEditButton">页面属性</label>
			<label index="pageEditTooltip">编辑当前页面属性</label>
			<label index="pageNewButton">新页面</label>
			<label index="pageNewTooltip">创建新页面作为当前页面的子页</label>
			<label index="pageDeleteButton">删除页面</label>
			<label index="pageDeleteTooltip">删除页面</label>
			<label index="pageHideButton">隐藏页面</label>
			<label index="pageHideTooltip">设置页面的可见性</label>
			<label index="pageShowHidden">显示隐藏元素</label>
			<label index="pageShowHiddenTooltip">切换隐藏内容显示</label>
			<label index="previewTitle">预览</label>
			<label index="previewTooltip">预览当前页</label>
			<label index="closeTitle">关闭</label>
			<label index="closeTooltip">关闭前台编辑</label>
			<label index="logoutTooltip">从总后台退出</label>
			<label index="openTooltip">打开前台编辑</label>
			<label index="clipboardTitle">剪切板</label>
			<label index="clipboardTooltip">使用粘贴板拷贝粘贴内容</label>
			<label index="dragWidgets">托拽内容到页面</label>
			<label index="js.dropMessage">拖拽内容元素到此处</label>
			<label index="js.loadingMessage">调入编辑表单</label>
			<label index="js.ajaxError">AJAX错误</label>
			<label index="js.generalError">看上去遇到了一些问题，请刷新页面再试或联系系统管理员</label>
			<label index="js.alreadyProcessingAction">已执行了一个操作，请等待.</label>
			<label index="js.newContentElement">新内容元素</label>
			<label index="js.newPage">新页面</label>
			<label index="js.editContentElement">编辑内容元素</label>
			<label index="js.editPageProperties">编辑页面属性</label>
			<label index="js.confirmDelete">你确定删除这个内容吗？</label>
			<label index="js.hideNotification">隐藏内容</label>
			<label index="js.unhideNotification">显示内容</label>
			<label index="js.moveNotification">移动内容</label>
			<label index="js.saveNotification">保存内容</label>
			<label index="js.closeNotification">关闭编辑表单</label>
			<label index="js.copyNotification">拷贝内容</label>
			<label index="js.cutNotification">剪切内容</label>
			<label index="js.pasteNotification">粘贴内容</label>
			<label index="js.updatingContent">更新内容</label>
		</languageKey>
	</data>
	<orig_hash type="array">
		<languageKey index="ch" type="array">
			<label index="closeEditMode" type="integer">82511326</label>
			<label index="openEditMode" type="integer">95985765</label>
			<label index="toggle_advanced" type="integer">162944094</label>
			<label index="toggle_simple" type="integer">33272291</label>
			<label index="copyIcon" type="integer">100361047</label>
			<label index="copyTitle" type="integer">207918426</label>
			<label index="cutIcon" type="integer">246625500</label>
			<label index="cutTitle" type="integer">131425711</label>
			<label index="deleteIcon" type="integer">254438473</label>
			<label index="deleteTitle" type="integer">239590607</label>
			<label index="downIcon" type="integer">9058343</label>
			<label index="downTitle" type="integer">213416758</label>
			<label index="editIcon" type="integer">131916066</label>
			<label index="editTitle" type="integer">55626841</label>
			<label index="hideIcon" type="integer">103439945</label>
			<label index="hideTitle" type="integer">107617460</label>
			<label index="newPageIcon" type="integer">246843316</label>
			<label index="newRecordIcon" type="integer">3944062</label>
			<label index="newRecordTitle" type="integer">198918291</label>
			<label index="pasteIcon" type="integer">57390677</label>
			<label index="pasteTitle" type="integer">232508073</label>
			<label index="refTitle" type="integer">28318206</label>
			<label index="unhideIcon" type="integer">77133724</label>
			<label index="unhideTitle" type="integer">8253833</label>
			<label index="dragIcon" type="integer">193613132</label>
			<label index="dragTitle" type="integer">26760095</label>
			<label index="upIcon" type="integer">39384216</label>
			<label index="upTitle" type="integer">20645477</label>
			<label index="saveButton" type="integer">211601612</label>
			<label index="saveCloseButton" type="integer">253224394</label>
			<label index="closeButton" type="integer">222113377</label>
			<label index="pageEditButton" type="integer">214814444</label>
			<label index="pageNewButton" type="integer">246843316</label>
			<label index="pageDeleteButton" type="integer">118474304</label>
			<label index="pageHideButton" type="integer">141445699</label>
			<label index="previewTitle" type="integer">52420219</label>
			<label index="previewTooltip" type="integer">105456483</label>
			<label index="closeTitle" type="integer">222113377</label>
			<label index="closeTooltip" type="integer">101610085</label>
			<label index="clipboardTitle" type="integer">37640827</label>
			<label index="js.ajaxError" type="integer">45847154</label>
			<label index="js.dropMessage" type="integer">80266425</label>
			<label index="js.loadingMessage" type="integer">174201607</label>
			<label index="js.generalError" type="integer">117452324</label>
			<label index="js.alreadyProcessingAction" type="integer">63387600</label>
			<label index="js.newContentElement" type="integer">252114627</label>
			<label index="js.newPage" type="integer">246843316</label>
			<label index="js.editContentElement" type="integer">123680817</label>
			<label index="js.editPageProperties" type="integer">94201029</label>
			<label index="js.confirmDelete" type="integer">23880942</label>
			<label index="js.hideNotification" type="integer">266220245</label>
			<label index="js.unhideNotification" type="integer">253456294</label>
			<label index="js.moveNotification" type="integer">161059661</label>
			<label index="js.saveNotification" type="integer">233808258</label>
			<label index="js.closeNotification" type="integer">137822861</label>
			<label index="js.copyNotification" type="integer">137669776</label>
			<label index="js.cutNotification" type="integer">184820707</label>
			<label index="js.pasteNotification" type="integer">46263459</label>
			<label index="js.updatingContent" type="integer">192078935</label>
			<label index="alertChange" type="integer">89207167</label>
			<label index="fe_users.tx_wecfeedit_beuser" type="integer">56944136</label>
			<label index="usersOnPage" type="integer">156168864</label>
			<label index="statusEditingOn" type="integer">128966832</label>
			<label index="statusEditingOff" type="integer">155159018</label>
			<label index="pageShowHidden" type="integer">131489452</label>
			<label index="openTooltip" type="integer">3729372</label>
			<label index="statusDeactivateEditing" type="integer">218862115</label>
			<label index="statusActivateEditing" type="integer">190679445</label>
			<label index="newRecordInTopOfColumnTitle" type="integer">157590534</label>
			<label index="pageEditTooltip" type="integer">101144899</label>
			<label index="pageNewTooltip" type="integer">62776538</label>
			<label index="pageDeleteTooltip" type="integer">137493095</label>
			<label index="pageHideTooltip" type="integer">76896420</label>
			<label index="dragWidgets" type="integer">180497188</label>
			<label index="pageShowHiddenTooltip" type="integer">41179083</label>
			<label index="logoutTooltip" type="integer">17774660</label>
			<label index="clipboardTooltip" type="integer">186317177</label>
		</languageKey>
	</orig_hash>
	<orig_text type="array">
		<languageKey index="ch" type="array">
			<label index="closeEditMode">close edit</label>
			<label index="openEditMode">Edit Page</label>
			<label index="toggle_advanced">Advanced</label>
			<label index="toggle_simple">Simple</label>
			<label index="copyIcon">Copy</label>
			<label index="copyTitle">Copy element</label>
			<label index="cutIcon">Cut</label>
			<label index="cutTitle">Cut this element</label>
			<label index="deleteIcon">Delete</label>
			<label index="deleteTitle">Delete this element</label>
			<label index="downIcon">Down</label>
			<label index="downTitle">Move this down</label>
			<label index="editIcon">Edit</label>
			<label index="editTitle">Edit this element by clicking on it</label>
			<label index="hideIcon">Hide</label>
			<label index="hideTitle">Hide this element</label>
			<label index="newPageIcon">New Page</label>
			<label index="newRecordIcon">New</label>
			<label index="newRecordTitle">New content after this element</label>
			<label index="pasteIcon">Paste</label>
			<label index="pasteTitle">Paste element after existing element</label>
			<label index="refTitle">Create reference</label>
			<label index="unhideIcon">Show</label>
			<label index="unhideTitle">Show this hidden element</label>
			<label index="dragIcon">Drag</label>
			<label index="dragTitle">Click to drag this element</label>
			<label index="upIcon">Up</label>
			<label index="upTitle">Move this up</label>
			<label index="saveButton">Save</label>
			<label index="saveCloseButton">Save &amp; Close</label>
			<label index="closeButton">Close</label>
			<label index="pageEditButton">Page Properties</label>
			<label index="pageNewButton">New Page</label>
			<label index="pageDeleteButton">Delete Page</label>
			<label index="pageHideButton">Hide Page</label>
			<label index="previewTitle">Preview</label>
			<label index="previewTooltip">Preview this page</label>
			<label index="closeTitle">Close</label>
			<label index="closeTooltip">Close Frontend Editing.</label>
			<label index="clipboardTitle">Clipboard</label>
			<label index="js.ajaxError">AJAX Error</label>
			<label index="js.dropMessage">Drop content here</label>
			<label index="js.loadingMessage">Loading editing form</label>
			<label index="js.generalError">It looks like we encountered some problems. Please reload the page and try again or contact your administrator.</label>
			<label index="js.alreadyProcessingAction">Already processing an action, please wait.</label>
			<label index="js.newContentElement">New Content Element</label>
			<label index="js.newPage">New Page</label>
			<label index="js.editContentElement">Edit Content Element</label>
			<label index="js.editPageProperties">Edit Page Properties</label>
			<label index="js.confirmDelete">Are you sure you want to delete this content?</label>
			<label index="js.hideNotification">Hiding content</label>
			<label index="js.unhideNotification">Unhiding content</label>
			<label index="js.moveNotification">Moving content</label>
			<label index="js.saveNotification">Saving content</label>
			<label index="js.closeNotification">Closing editing form</label>
			<label index="js.copyNotification">Copying content</label>
			<label index="js.cutNotification">Cutting content</label>
			<label index="js.pasteNotification">Pasting content</label>
			<label index="js.updatingContent">Updating content</label>
			<label index="alertChange">This change will affect which fields are available in the form. Please save this record in order to get a new field set.</label>
			<label index="fe_users.tx_wecfeedit_beuser">Backend User To Link To</label>
			<label index="usersOnPage">WARNING: Following users are editing this page:</label>
			<label index="statusEditingOn">Editing On</label>
			<label index="statusEditingOff">Editing Off</label>
			<label index="pageShowHidden">Show Hidden Content Elements</label>
			<label index="openTooltip">Open Frontend Editing.</label>
			<label index="statusDeactivateEditing">Deactivate Editing</label>
			<label index="statusActivateEditing">Activate Editing</label>
			<label index="newRecordInTopOfColumnTitle">New content in top of this column</label>
			<label index="pageEditTooltip">Edit page properties of the current page.</label>
			<label index="pageNewTooltip">Create a new page as subpage to the current page.</label>
			<label index="pageDeleteTooltip">Delete this page.</label>
			<label index="pageHideTooltip">Set the visibility of this page to hidden.</label>
			<label index="dragWidgets">Drag widgets onto the page.</label>
			<label index="pageShowHiddenTooltip">Toggle the display of hidden content elements on or off.</label>
			<label index="logoutTooltip">Logout from TYPO3 Backend.</label>
			<label index="clipboardTooltip">Use the clipboard to copy and paste content.</label>
		</languageKey>
	</orig_text>
</T3locallangExt>