<?xml version="1.0" encoding="utf-8" standalone="yes" ?>
<T3locallangExt>
	<data type="array">
		<languageKey index="ch" type="array">
			<label index="tx_kestats_statdata">统计数据</label>
			<label index="tx_kestats_statdata.type">类型</label>
			<label index="tx_kestats_statdata.category">类目</label>
			<label index="tx_kestats_statdata.element_uid">统计元素的记录编号</label>
			<label index="tx_kestats_statdata.element_pid">统计元素的页面编号</label>
			<label index="tx_kestats_statdata.element_title">统计元素的标题</label>
			<label index="tx_kestats_statdata.element_language">统计元素的语言</label>
			<label index="tx_kestats_statdata.element_type">统计元素的类型</label>
			<label index="tx_kestats_statdata.counter">计数器</label>
			<label index="tx_kestats_statdata.year">年</label>
			<label index="tx_kestats_statdata.month">月</label>
			<label index="tx_kestats_statdata.parent_uid">父记录编号</label>
		</languageKey>
	</data>
	<orig_hash type="array">
		<languageKey index="ch" type="array">
			<label index="tx_kestats_statdata" type="integer">184073060</label>
			<label index="tx_kestats_statdata.type" type="integer">93969614</label>
			<label index="tx_kestats_statdata.category" type="integer">206500690</label>
			<label index="tx_kestats_statdata.element_uid" type="integer">31072530</label>
			<label index="tx_kestats_statdata.element_pid" type="integer">229767869</label>
			<label index="tx_kestats_statdata.element_title" type="integer">187422582</label>
			<label index="tx_kestats_statdata.element_language" type="integer">118457317</label>
			<label index="tx_kestats_statdata.element_type" type="integer">163098656</label>
			<label index="tx_kestats_statdata.counter" type="integer">143047539</label>
			<label index="tx_kestats_statdata.year" type="integer">139254902</label>
			<label index="tx_kestats_statdata.month" type="integer">121859988</label>
			<label index="tx_kestats_statdata.parent_uid" type="integer">168933561</label>
		</languageKey>
	</orig_hash>
	<orig_text type="array">
		<languageKey index="ch" type="array">
			<label index="tx_kestats_statdata">statistical data</label>
			<label index="tx_kestats_statdata.type">type</label>
			<label index="tx_kestats_statdata.category">category</label>
			<label index="tx_kestats_statdata.element_uid">uid of the counted element</label>
			<label index="tx_kestats_statdata.element_pid">pid of the counted element</label>
			<label index="tx_kestats_statdata.element_title">title of the counted element</label>
			<label index="tx_kestats_statdata.element_language">language of the counted element</label>
			<label index="tx_kestats_statdata.element_type">type of the counted element (fx. pagetype)</label>
			<label index="tx_kestats_statdata.counter">counter</label>
			<label index="tx_kestats_statdata.year">year</label>
			<label index="tx_kestats_statdata.month">month</label>
			<label index="tx_kestats_statdata.parent_uid">parent uid</label>
		</languageKey>
	</orig_text>
</T3locallangExt>