<?xml version="1.0" encoding="utf-8" standalone="yes" ?>
<T3locallangExt>
	<data type="array">
		<languageKey index="ch" type="array">
			<label index="pi_flexform.sheetTitle.sDEF">通用</label>
			<label index="pi_flexform.formId">选择表单</label>
			<label index="pi_flexform.allowedGroups">允许用户组</label>
			<label index="pi_flexform.inputAdminField">输入管理字段</label>
			<label index="pi_flexform.noFilterShowAll">如果没有过滤器则显示所</label>
			<label index="pi_flexform.inputOnForm">在表单输入</label>
			<label index="pi_flexform.inputStartDate">输入开始时间</label>
			<label index="pi_flexform.inputEndDate">输入结束时间</label>
			<label index="pi_flexform.inputApplyLimit">应用日期限制到</label>
			<label index="pi_flexform.inputApplyLimit.I.0">没有人</label>
			<label index="pi_flexform.inputApplyLimit.I.1">所有</label>
			<label index="pi_flexform.inputApplyLimit.I.2">高级管理用户</label>
			<label index="pi_flexform.inputApplyLimit.I.3">所有除了超级管理员</label>
			<label index="pi_flexform.showNoAvailableInformation">没有可用信息</label>
			<label index="pi_flexform.showNoAvailableInformation.I.0">显示一个信息</label>
			<label index="pi_flexform.showNoAvailableInformation.I.1">不要显示信息</label>
			<label index="pi_flexform.showNoAvailableInformation.I.2">不要显示扩展</label>
			<label index="pi_flexform.maxItems">最大显示数量</label>
			<label index="pi_flexform.sheetTitle.sInput">输入控制</label>
			<label index="pi_flexform.noNewButton">没有新增按钮</label>
			<label index="pi_flexform.noEditButton">没有编辑按钮</label>
			<label index="pi_flexform.noDeleteButton">没有删除按钮</label>
			<label index="pi_flexform.deleteButtonOnlyForCruser">对于数据创建用户添加删除按钮</label>
			<label index="pi_flexform.submitButton">添加一个发布按钮（用在表单上）</label>
			<label index="pi_flexform.sheetTitle.sAdvanced">高级</label>
			<label index="pi_flexform.permanentFilter">固定过滤器</label>
			<label index="pi_flexform.addFragment">添加一个连接目标（内容ID）</label>
			<label index="pi_flexform.allowQueryProperty">允许使用查询属性</label>
			<label index="pi_flexform.allowExec">允许执行导出功能</label>
			<label index="pi_flexform.helpPage">帮助页面</label>
			<label index="pi_flexform.help">帮助</label>
			<label index="pi_flexform.storagePage">存储页面</label>
			<label index="pi_flexform.caching">应用缓存到：</label>
			<label index="pi_flexform.caching.I.0">关闭按钮</label>
			<label index="pi_flexform.caching.I.1">表单箭头</label>
			<label index="pi_flexform.caching.I.2">子表单箭头</label>
			<label index="pi_flexform.caching.I.3">表单页面浏览器</label>
			<label index="pi_flexform.caching.I.4">子表单页面浏览器</label>
			<label index="pi_flexform.pagesToClear">更新数据时缓存将被更新的页面</label>
			<label index="button.edit">编辑</label>
			<label index="button.save">保存</label>
			<label index="button.saveandclose">保存并关闭</label>
			<label index="button.saveandshow">保存并显示</label>
			<label index="button.close">关闭</label>
			<label index="button.export">用csv导出</label>
			<label index="button.new">新建</label>
			<label index="button.delete">删除</label>
			<label index="button.inputMode">进入编辑模式</label>
			<label index="button.toggleMode">编辑模式</label>
			<label index="button.generateRTF">产生RTF</label>
			<label index="button.search">搜索</label>
			<label index="button.leftArrow">上一个</label>
			<label index="button.rightArrow">下一个</label>
			<label index="button.backward">上一个</label>
			<label index="button.forward">下一个</label>
			<label index="button.backwardFirst">第一个</label>
			<label index="button.forwardLast">最后一个</label>
			<label index="button.up">上</label>
			<label index="button.down">下</label>
			<label index="button.deleteItem">删除项目</label>
			<label index="button.print">打印</label>
			<label index="button.help">帮助</label>
			<label index="button.mail">发送邮件</label>
			<label index="button.submit">发送表单</label>
			<label index="button.orderAsc">顺序排序</label>
			<label index="button.orderDesc">逆序排序</label>
			<label index="button.saveExportConfiguration">保存导出配置</label>
			<label index="button.loadExportConfiguration">调入导出配置</label>
			<label index="button.deleteExportConfiguration">删除导出配置</label>
			<label index="button.toggleExportDisplay_1">显示所有字段</label>
			<label index="button.toggleExportDisplay_0">仅显示所选字段</label>
			<label index="icon.required">必须字段</label>
			<label index="icon.new">新建</label>
			<label index="itemviewer.days.0">周一</label>
			<label index="itemviewer.days.1">周二</label>
			<label index="itemviewer.days.2">周三</label>
			<label index="itemviewer.days.3">周四</label>
			<label index="itemviewer.days.4">周五</label>
			<label index="itemviewer.days.5">周六</label>
			<label index="itemviewer.days.6">周日</label>
			<label index="itemviewer.checkboxSelected">选择</label>
			<label index="itemviewer.checkboxNotSelected">没有选择</label>
			<label index="itemviewer.radioSelected">选择</label>
			<label index="itemviewer.radioNotSelected">没有选择</label>
			<label index="itemviewer.yes">是</label>
			<label index="itemviewer.no">否</label>
			<label index="itemviewer.configuration">配置</label>
			<label index="itemviewer.configurationGroup">群组</label>
		</languageKey>
	</data>
	<orig_hash type="array">
		<languageKey index="ch" type="array">
			<label index="pi_flexform.sheetTitle.sDEF" type="integer">14366585</label>
			<label index="pi_flexform.formId" type="integer">106496129</label>
			<label index="pi_flexform.allowedGroups" type="integer">22096279</label>
			<label index="pi_flexform.inputAdminField" type="integer">26297566</label>
			<label index="pi_flexform.noFilterShowAll" type="integer">120712599</label>
			<label index="pi_flexform.inputOnForm" type="integer">7455840</label>
			<label index="pi_flexform.inputStartDate" type="integer">156417307</label>
			<label index="pi_flexform.inputEndDate" type="integer">243458068</label>
			<label index="pi_flexform.inputApplyLimit" type="integer">119687987</label>
			<label index="pi_flexform.inputApplyLimit.I.0" type="integer">192318586</label>
			<label index="pi_flexform.inputApplyLimit.I.1" type="integer">186422474</label>
			<label index="pi_flexform.inputApplyLimit.I.2" type="integer">144664440</label>
			<label index="pi_flexform.inputApplyLimit.I.3" type="integer">177118005</label>
			<label index="pi_flexform.showNoAvailableInformation" type="integer">223826818</label>
			<label index="pi_flexform.showNoAvailableInformation.I.0" type="integer">262670053</label>
			<label index="pi_flexform.showNoAvailableInformation.I.1" type="integer">265717419</label>
			<label index="pi_flexform.showNoAvailableInformation.I.2" type="integer">201873115</label>
			<label index="pi_flexform.maxItems" type="integer">62297999</label>
			<label index="pi_flexform.sheetTitle.sInput" type="integer">148659935</label>
			<label index="pi_flexform.noNewButton" type="integer">26403713</label>
			<label index="pi_flexform.noEditButton" type="integer">69742740</label>
			<label index="pi_flexform.noDeleteButton" type="integer">32640630</label>
			<label index="pi_flexform.deleteButtonOnlyForCruser" type="integer">243093937</label>
			<label index="pi_flexform.submitButton" type="integer">222617967</label>
			<label index="pi_flexform.sheetTitle.sAdvanced" type="integer">162944094</label>
			<label index="pi_flexform.permanentFilter" type="integer">191361010</label>
			<label index="pi_flexform.addFragment" type="integer">52134768</label>
			<label index="pi_flexform.allowQueryProperty" type="integer">149560132</label>
			<label index="pi_flexform.allowExec" type="integer">87539555</label>
			<label index="pi_flexform.helpPage" type="integer">192209835</label>
			<label index="pi_flexform.help" type="integer">111308628</label>
			<label index="pi_flexform.storagePage" type="integer">239051680</label>
			<label index="pi_flexform.caching" type="integer">35035700</label>
			<label index="pi_flexform.caching.I.0" type="integer">82310311</label>
			<label index="pi_flexform.caching.I.1" type="integer">190301412</label>
			<label index="pi_flexform.caching.I.2" type="integer">134441557</label>
			<label index="pi_flexform.caching.I.3" type="integer">77430023</label>
			<label index="pi_flexform.caching.I.4" type="integer">251502843</label>
			<label index="button.edit" type="integer">131916066</label>
			<label index="button.save" type="integer">211601612</label>
			<label index="button.saveandclose" type="integer">125326617</label>
			<label index="button.saveandshow" type="integer">153613873</label>
			<label index="button.close" type="integer">222113377</label>
			<label index="button.export" type="integer">111564014</label>
			<label index="button.new" type="integer">3944062</label>
			<label index="button.delete" type="integer">254438473</label>
			<label index="button.inputMode" type="integer">248022736</label>
			<label index="button.toggleMode" type="integer">136089991</label>
			<label index="button.generateRTF" type="integer">63032608</label>
			<label index="button.search" type="integer">20138052</label>
			<label index="button.leftArrow" type="integer">231864181</label>
			<label index="button.rightArrow" type="integer">17482704</label>
			<label index="button.backward" type="integer">231864181</label>
			<label index="button.forward" type="integer">17482704</label>
			<label index="button.backwardFirst" type="integer">133912045</label>
			<label index="button.forwardLast" type="integer">223720198</label>
			<label index="button.up" type="integer">39384216</label>
			<label index="button.down" type="integer">9058343</label>
			<label index="button.deleteItem" type="integer">242014136</label>
			<label index="button.print" type="integer">20822564</label>
			<label index="button.help" type="integer">111308628</label>
			<label index="button.mail" type="integer">139434930</label>
			<label index="button.submit" type="integer">139479898</label>
			<label index="button.orderAsc" type="integer">207656340</label>
			<label index="button.orderDesc" type="integer">61063542</label>
			<label index="button.saveExportConfiguration" type="integer">176410264</label>
			<label index="button.loadExportConfiguration" type="integer">124823543</label>
			<label index="button.deleteExportConfiguration" type="integer">177291175</label>
			<label index="button.toggleExportDisplay_1" type="integer">91231812</label>
			<label index="button.toggleExportDisplay_0" type="integer">113726040</label>
			<label index="icon.required" type="integer">27230780</label>
			<label index="icon.new" type="integer">3944062</label>
			<label index="itemviewer.days.0" type="integer">116937262</label>
			<label index="itemviewer.days.1" type="integer">38159247</label>
			<label index="itemviewer.days.2" type="integer">127320419</label>
			<label index="itemviewer.days.3" type="integer">126543600</label>
			<label index="itemviewer.days.4" type="integer">204714296</label>
			<label index="itemviewer.days.5" type="integer">146212113</label>
			<label index="itemviewer.days.6" type="integer">164733076</label>
			<label index="itemviewer.checkboxSelected" type="integer">152781869</label>
			<label index="itemviewer.checkboxNotSelected" type="integer">115363391</label>
			<label index="itemviewer.radioSelected" type="integer">152781869</label>
			<label index="itemviewer.radioNotSelected" type="integer">115363391</label>
			<label index="itemviewer.yes" type="integer">154974727</label>
			<label index="itemviewer.no" type="integer">196073266</label>
			<label index="itemviewer.configuration" type="integer">39122498</label>
			<label index="itemviewer.configurationGroup" type="integer">3749651</label>
			<label index="pi_flexform.pagesToClear" type="integer">223072485</label>
		</languageKey>
	</orig_hash>
	<orig_text type="array">
		<languageKey index="ch" type="array">
			<label index="pi_flexform.sheetTitle.sDEF">General</label>
			<label index="pi_flexform.formId">Select form</label>
			<label index="pi_flexform.allowedGroups">Allowed groups</label>
			<label index="pi_flexform.inputAdminField">Input Admin Field</label>
			<label index="pi_flexform.noFilterShowAll">Show all if no filter</label>
			<label index="pi_flexform.inputOnForm">Input on form</label>
			<label index="pi_flexform.inputStartDate">Input start date</label>
			<label index="pi_flexform.inputEndDate">Input end date</label>
			<label index="pi_flexform.inputApplyLimit">Apply date limit to</label>
			<label index="pi_flexform.inputApplyLimit.I.0">Nobody</label>
			<label index="pi_flexform.inputApplyLimit.I.1">All</label>
			<label index="pi_flexform.inputApplyLimit.I.2">&quot;Admin plus&quot; users</label>
			<label index="pi_flexform.inputApplyLimit.I.3">All excluding &quot;Super Admin&quot;</label>
			<label index="pi_flexform.showNoAvailableInformation">In no information available</label>
			<label index="pi_flexform.showNoAvailableInformation.I.0">Show a message</label>
			<label index="pi_flexform.showNoAvailableInformation.I.1">Do not show a message</label>
			<label index="pi_flexform.showNoAvailableInformation.I.2">Do not show the extension</label>
			<label index="pi_flexform.maxItems">Max number of items</label>
			<label index="pi_flexform.sheetTitle.sInput">Input controls</label>
			<label index="pi_flexform.noNewButton">No &quot;new&quot; button</label>
			<label index="pi_flexform.noEditButton">No &quot;edit&quot; button</label>
			<label index="pi_flexform.noDeleteButton">No &quot;delete&quot; button</label>
			<label index="pi_flexform.deleteButtonOnlyForCruser">Add a &quot;delete&quot; button only for records created by the user</label>
			<label index="pi_flexform.submitButton">Add a &quot;submit&quot; button (to be used with a form)</label>
			<label index="pi_flexform.sheetTitle.sAdvanced">Advanced</label>
			<label index="pi_flexform.permanentFilter">Permanent filter</label>
			<label index="pi_flexform.addFragment">Add a fragment(#content id) to links</label>
			<label index="pi_flexform.allowQueryProperty">Allow the use of the &quot;query&quot; property</label>
			<label index="pi_flexform.allowExec">Allow the use of the exec function in export</label>
			<label index="pi_flexform.helpPage">Help page</label>
			<label index="pi_flexform.help">Help</label>
			<label index="pi_flexform.storagePage">Storage page</label>
			<label index="pi_flexform.caching">Apply caching to:</label>
			<label index="pi_flexform.caching.I.0">Close button</label>
			<label index="pi_flexform.caching.I.1">Arrows in form</label>
			<label index="pi_flexform.caching.I.2">Arrows in subform</label>
			<label index="pi_flexform.caching.I.3">Page browser in form</label>
			<label index="pi_flexform.caching.I.4">Page browser in subform</label>
			<label index="button.edit">Edit</label>
			<label index="button.save">Save</label>
			<label index="button.saveandclose">Save and close</label>
			<label index="button.saveandshow">Save and show</label>
			<label index="button.close">Close</label>
			<label index="button.export">Export in csv</label>
			<label index="button.new">New</label>
			<label index="button.delete">Delete</label>
			<label index="button.inputMode">Enter in edit mode</label>
			<label index="button.toggleMode">Toggle mode</label>
			<label index="button.generateRTF">Generate RTF</label>
			<label index="button.search">Search</label>
			<label index="button.leftArrow">Previous</label>
			<label index="button.rightArrow">Next</label>
			<label index="button.backward">Previous</label>
			<label index="button.forward">Next</label>
			<label index="button.backwardFirst">First</label>
			<label index="button.forwardLast">Last</label>
			<label index="button.up">Up</label>
			<label index="button.down">Down</label>
			<label index="button.deleteItem">Delete Item</label>
			<label index="button.print">Print</label>
			<label index="button.help">Help</label>
			<label index="button.mail">Send the email</label>
			<label index="button.submit">Submit the form</label>
			<label index="button.orderAsc">Sort by ascending order</label>
			<label index="button.orderDesc">Sort by descending order</label>
			<label index="button.saveExportConfiguration">Save export configuration</label>
			<label index="button.loadExportConfiguration">Load export configuration</label>
			<label index="button.deleteExportConfiguration">Delete export configuration</label>
			<label index="button.toggleExportDisplay_1">Display all fields</label>
			<label index="button.toggleExportDisplay_0">Display only selected fields</label>
			<label index="icon.required">Required field</label>
			<label index="icon.new">New</label>
			<label index="itemviewer.days.0">Monday</label>
			<label index="itemviewer.days.1">Twesday</label>
			<label index="itemviewer.days.2">Wednesday</label>
			<label index="itemviewer.days.3">Thursday</label>
			<label index="itemviewer.days.4">Friday</label>
			<label index="itemviewer.days.5">Saturday</label>
			<label index="itemviewer.days.6">Sunday</label>
			<label index="itemviewer.checkboxSelected">Selected</label>
			<label index="itemviewer.checkboxNotSelected">Not selected</label>
			<label index="itemviewer.radioSelected">Selected</label>
			<label index="itemviewer.radioNotSelected">Not selected</label>
			<label index="itemviewer.yes">Yes</label>
			<label index="itemviewer.no">No</label>
			<label index="itemviewer.configuration">Configuration</label>
			<label index="itemviewer.configurationGroup">Group</label>
			<label index="pi_flexform.pagesToClear">Pages whose cache will be cleared on update of the data</label>
		</languageKey>
	</orig_text>
</T3locallangExt>