<?xml version="1.0" encoding="utf-8" standalone="yes" ?>
<T3locallangExt>
	<data type="array">
		<languageKey index="ch" type="array">
			<label index="labels.openInNewWindow">在新窗口中打开</label>
			<label index="labels.goBack">返回</label>
			<label index="labels.makeShortcut">创建此页面的快捷方式?</label>
			<label index="labels.makeBookmark">创建书签到本页</label>
			<label index="labels.lockedRecord">用户'%s' 在%s之前开始编辑此记录.</label>
			<label index="labels.lockedRecord_content">用户'%s'在%s之前开始编辑此页面上的内容.</label>
			<label index="labels.lockedRecordUser">用户 %s '%s' 开始编辑这条记录，在 %s 之前.</label>
			<label index="labels.lockedRecordUser_content">用户 %s '%s' 开始编辑这个内容，在 %s 之前.</label>
			<label index="labels.user">用户</label>
			<label index="labels.beUser">后台用户</label>
			<label index="labels.feUser">前台用户</label>
			<label index="labels.unknownUser">-未知-</label>
			<label index="labels.showRecords">显示记录</label>
			<label index="labels.path">路径</label>
			<label index="labels.resetFilter">重设过滤器</label>
			<label index="labels.table">表格</label>
			<label index="labels.upOneLevel">向上一层</label>
			<label index="labels.expandTable">扩展表格</label>
			<label index="labels.collapseTable">折叠表格</label>
			<label index="labels.enterSearchString">搜索字符串:</label>
			<label index="labels.enterSearchLevels">本页|向下1层|向下2层|向下3层|向下4层</label>
			<label index="labels.noEditPermission">对不起,您没有执行此更改的适当许可.</label>
			<label index="labels.fieldsMissing">黄色感叹号标识出来的域没有被正确填入,请完整的完成它们.</label>
			<label index="labels.fieldsChanged">表单中有未被保存的更改!
您想不保存而继续吗?</label>
			<label index="labels.noRTEfound">注意：此域仅可用Rich Text编辑器编辑.当前无编辑器可用.</label>
			<label index="labels.showPalettes">显示二级选项(选项板)</label>
			<label index="labels.showDescriptions">显示域描述</label>
			<label index="labels.disableRTE">禁用Rich Text编辑器(RTE)</label>
			<label index="labels._CONTROL_">控制</label>
			<label index="labels._PATH_">路径</label>
			<label index="labels._LOCALIZATION_">定位</label>
			<label index="labels.setFields">设置域</label>
			<label index="labels.search">搜索</label>
			<label index="labels.author">作者:</label>
			<label index="labels.note">注释:</label>
			<label index="labels.category">类别:</label>
			<label index="labels.reload">重新加载</label>
			<label index="labels.csv">下载CSV文件</label>
			<label index="labels.clear_cache">清除此页面的缓存</label>
			<label index="labels.no_title">无标题</label>
			<label index="labels.cancel">取消</label>
			<label index="labels.hidden">隐藏</label>
			<label index="labels.starttime">开始</label>
			<label index="labels.endtime">结束</label>
			<label index="labels.minutesHoursDaysYears">分|时|天|年</label>
			<label index="labels.menu">菜单:</label>
			<label index="labels.showPage">查看网页</label>
			<label index="labels.showList">显示记录列表</label>
			<label index="labels.days">天</label>
			<label index="labels.depth_0">此页面</label>
			<label index="labels.depth_1">1 层</label>
			<label index="labels.depth_2">2 层</label>
			<label index="labels.depth_3">3 层</label>
			<label index="labels.depth_4">4 层</label>
			<label index="labels.depth_infi">无限</label>
			<label index="labels.allow">允许</label>
			<label index="labels.deny">拒绝</label>
			<label index="labels.automatic">自动</label>
			<label index="labels.enabled">打开</label>
			<label index="labels.show">显示</label>
			<label index="labels.generalTab">普通</label>
			<label index="labels.refresh">刷新目录树</label>
			<label index="labels.temporaryDBmount">取消临时加载的数据库</label>
			<label index="labels.refreshList">刷新列表</label>
			<label index="labels.close">关闭</label>
			<label index="labels.new">新建</label>
			<label index="labels.createNewPage">创建新 %s</label>
			<label index="labels.createNewRecord">创建新 %s，在页面 &quot;%s&quot;</label>
			<label index="labels.createNewRecordRootLevel">创建新 %s，在根级别</label>
			<label index="labels.editPage">编辑 %s &quot;%s&quot;</label>
			<label index="labels.editRecord">编辑 %s &quot;%s&quot;，在页面 &quot;%s&quot;</label>
			<label index="labels.editRecordNoTitle">编辑 %s 在页面 &quot;%s&quot;</label>
			<label index="labels.editRecordRootLevel">编辑%s &quot;%s&quot; 在根级别</label>
			<label index="labels.rootLevel">根级别</label>
			<label index="labels.addnew">添加新</label>
			<label index="labels.toggleall">切换所有</label>
			<label index="labels.selected">已选项目</label>
			<label index="labels.items">可用项目</label>
			<label index="labels.remove_selected">移去所选条目</label>
			<label index="labels.move_to_top">将所选条目移至顶部</label>
			<label index="labels.move_up">向上移动所选条目</label>
			<label index="labels.move_down">向下移动所选条目</label>
			<label index="labels.move_to_bottom">将所选条目移至底部</label>
			<label index="labels.move">移动此项</label>
			<label index="labels.browse_file">浏览文件</label>
			<label index="labels.browse_db">浏览记录</label>
			<label index="labels.clipInsert_file">从剪贴板插入%s文件</label>
			<label index="labels.clipInsert_db">从剪贴板插入%s记录</label>
			<label index="labels.generalOptions">常规选项:</label>
			<label index="labels.generalOptions_more">常规选项（继续）：</label>
			<label index="labels.allTables">[全部表格]</label>
			<label index="labels.moreOptions">更多选项...</label>
			<label index="labels.noMatchingValue">无效数值(&quot;%s&quot;)</label>
			<label index="labels.thumbmode_clip">显示剪贴板上的缩略图</label>
			<label index="labels.copymode">复制条目代替移动条目</label>
			<label index="labels.clipNoEl">无元素</label>
			<label index="labels.cliptabs">剪贴板 #</label>
			<label index="labels.removeItem">移除条目</label>
			<label index="labels.holdDownCTRL">重要： 切换此表的元素时按住CTRL键！</label>
			<label index="labels.revertSelection">还原选择</label>
			<label index="labels.setAllCheckboxes">选中全部复选框</label>
			<label index="labels.checkAll">选择所有</label>
			<label index="labels.uncheckAll">取消选择所有</label>
			<label index="labels.changeInOrig">在原始数据中更改</label>
			<label index="labels.expandAll">扩展全部</label>
			<label index="labels.new_section">创建：</label>
			<label index="labels.count">数量：</label>
			<label index="labels.findRecord">搜索记录：</label>
			<label index="labels.noRecordFound">没有发现记录</label>
			<label index="alttext.suggestSearching">搜索...</label>
			<label index="ver.online">在线</label>
			<label index="ver.mgm">版本管理</label>
			<label index="ver.selVer">选择版本：</label>
			<label index="ver.swap">交换/公布</label>
			<label index="ver.swapPage">公布该页面版本,包括内容</label>
			<label index="TYPO3_Element_Browser">元素浏览器</label>
			<label index="show_item.php.viewItem">查看条目</label>
			<label index="show_item.php.file">文件</label>
			<label index="show_item.php.dimensions">尺寸</label>
			<label index="show_item.php.filesize">大小</label>
			<label index="show_item.php.pixels">像素</label>
			<label index="show_item.php.files">文件</label>
			<label index="show_item.php.cannotDisplayArchive">对不起 TYPO3_CONF_VARS[BE][disable_exec_function] 没有设置，所以不能显示存档内容</label>
			<label index="show_item.php.table">表格：</label>
			<label index="show_item.php.ftp_area">FTP 区域</label>
			<label index="db_new.php.pagetitle">新记录</label>
			<label index="db_new.php.after">之后</label>
			<label index="db_new.php.inside">内部</label>
			<label index="file_upload.php.pagetitle">上传文件</label>
			<label index="file_upload.php.submit">上传文件</label>
			<label index="file_upload.php.files">文件</label>
			<label index="file_upload.php.number_of_files">文件数量：</label>
			<label index="file_rename.php.pagetitle">重命名</label>
			<label index="file_rename.php.submit">重命名</label>
			<label index="file_edit.php.pagetitle">编辑</label>
			<label index="file_edit.php.submit">保存</label>
			<label index="file_edit.php.saveAndClose">保存并关闭</label>
			<label index="file_edit.php.coundNot">无法编辑此文件类型.&lt;br /&gt;文件必须有一个后缀如:&lt;br /&gt;&lt;br /&gt; &lt;b&gt;%s&lt;/b&gt;</label>
			<label index="file_newfolder.php.pagetitle">新文件或文件夹</label>
			<label index="file_newfolder.php.submit">创建文件夹</label>
			<label index="file_newfolder.php.folders">文件夹</label>
			<label index="file_newfolder.php.newfile_submit">创建文件</label>
			<label index="file_newfolder.php.newfile">创建新的文本文件</label>
			<label index="file_newfolder.php.number_of_folders">文件夹数量：</label>
			<label index="file_clipupload.php.warning_head">上传路径错误</label>
			<label index="file_clipupload.php.warning">未找到上传文件夹.您应该首先在某一个安装的根目录中创建一个TEMP(&quot;_temp_&quot;)文件夹!</label>
			<label index="mess.redraw">刷新页面将丢失当前数据. 您想继续吗?</label>
			<label index="mess.delete">您确定要删除&quot;%s&quot;?</label>
			<label index="mess.deleteClip">您确定要删除剪贴板中所有选中的元素(%s)?</label>
			<label index="mess.refresh_login">您的登录可能已到期. 您想现在重新刷新吗?</label>
			<label index="mess.refresh_login_refresh_button">保持登录！</label>
			<label index="mess.refresh_logout_button">退出</label>
			<label index="mess.refresh_direct_logout_button">No,退出</label>
			<label index="mess.refresh_login_countdown">{0}  秒</label>
			<label index="mess.refresh_login_countdown_singular">{0}  秒</label>
			<label index="mess.refresh_login_logging_in">登录...</label>
			<label index="mess.refresh_login_failed">登录失败</label>
			<label index="mess.refresh_login_failed_message">密码不正确</label>
			<label index="mess.refresh_login_title">刷新</label>
			<label index="mess.refresh_login_username">用户名</label>
			<label index="mess.refresh_login_password">密码</label>
			<label index="mess.refresh_login_button">登录</label>
			<label index="mess.refresh_login_emptyPassword">不允许空密码</label>
			<label index="mess.please_wait">请等待...</label>
			<label index="mess.be_locked">因为维护后台已经锁定，保持浏览器打开状态，维护完毕后后台将自动可用</label>
			<label index="mess.login_about_to_expire">登录已经过期，请确认你将保持登录</label>
			<label index="mess.login_about_to_expire_title">登录过期提示</label>
			<label index="mess.login_expired">登录已经过期，你需要重新登录，否则请关闭此窗口</label>
			<label index="mess.noSelItemForEdit">在您编辑前请在列表中选择一个或多个条目.</label>
			<label index="mess.onChangeAlert">此更改将影响表单中的有效域.
您想现在保存并刷新显示?</label>
			<label index="mess.move_into">将&quot;%s&quot;移动到&quot;%s&quot;中?</label>
			<label index="mess.move_after">将&quot;%s&quot;移动到&quot;%s&quot;之后?</label>
			<label index="mess.copy_into">将&quot;%s&quot;复制到&quot;%s&quot;中?</label>
			<label index="mess.copy_after">将&quot;%s&quot;复制到&quot;%s&quot;之后?</label>
			<label index="mess.copycb_into">从剪贴板复制所有元素(%s)到&quot;%s&quot;中?</label>
			<label index="mess.copycb_after">从剪贴板复制所有元素(%s)到&quot;%s&quot;之后的位置?</label>
			<label index="mess.movecb_into">从剪贴板移动所有元素(%s)到&quot;%s&quot;中?</label>
			<label index="mess.movecb_after">从剪贴板移动所有元素(%s)到&quot;%s&quot;之后的位置?</label>
			<label index="rm.menu">[菜单]</label>
			<label index="rm.saveDoc">保存文档</label>
			<label index="rm.saveDocShow">保存文档并查看页面</label>
			<label index="rm.saveCloseDoc">保存并关闭</label>
			<label index="rm.translationSaveDoc">翻译完毕，保存并关闭</label>
			<label index="rm.translationSaveDocClear">翻译未结束，保存</label>
			<label index="rm.saveCloseAllDocs">保存并关闭所有文档</label>
			<label index="rm.saveNewDoc">保存文档并创建一个新文档</label>
			<label index="rm.closeDoc">关闭文档</label>
			<label index="rm.closeAllDocs">关闭所有文档</label>
			<label index="rm.clearCache_clearCache">清除缓存</label>
			<label index="rm.clearCache_thisPage">此页面</label>
			<label index="rm.clearCache_all">清除前台缓存</label>
			<label index="rm.clearCache_pages">清除页面缓存</label>
			<label index="rm.clearCache_allTypo3Conf">清除typo3conf/中的缓存</label>
			<label index="rm.clearCacheMenu_all">清理所有缓存</label>
			<label index="rm.clearCacheMenu_pages">清理页面缓存</label>
			<label index="rm.clearCacheMenu_allTypo3Conf">清理配置缓存</label>
			<label index="rm.adminFunctions">管理功能</label>
			<label index="rm.edit">编辑</label>
			<label index="rm.export">导出</label>
			<label index="rm.delete">删除</label>
			<label index="buttons.logout">退出</label>
			<label index="buttons.exit">退出</label>
			<label index="buttons.selMenu_modules">模块</label>
			<label index="buttons.clear">清除</label>
			<label index="buttons.clipboard">剪贴板</label>
			<label index="cm.copy">复制</label>
			<label index="cm.cut">剪切</label>
			<label index="cm.view">显示</label>
			<label index="cm.edit">编辑</label>
			<label index="cm.new">新建</label>
			<label index="cm.pasteinto">粘贴到</label>
			<label index="cm.pasteafter">粘贴其后</label>
			<label index="cm.select">选择</label>
			<label index="cm.deselect">取消选择</label>
			<label index="cm.selectto">选择到</label>
			<label index="cm.deselectto">取消选择到</label>
			<label index="cm.delete">删除</label>
			<label index="cm.hide">隐藏</label>
			<label index="cm.unhide">取消隐藏</label>
			<label index="cm.upload">上传文件</label>
			<label index="cm.rename">重命名</label>
			<label index="cm.open">打开</label>
			<label index="cm.save">保存</label>
			<label index="cm.unzip">Unzip</label>
			<label index="cm.info">信息</label>
			<label index="cm.createnew">创建新的</label>
			<label index="cm.tempMountPoint">作为根安装</label>
			<label index="cm.copyPage_into">拷贝进</label>
			<label index="cm.copyPage_after">拷贝当前页后</label>
			<label index="cm.movePage_into">移动进</label>
			<label index="cm.movePage_after">移动当前页后</label>
			<label index="cm.copyFolder_into">拷贝文件夹进</label>
			<label index="cm.moveFolder_into">移动文件夹进</label>
			<label index="cm.createNewRelation">创建新关系</label>
			<label index="cm.branchActions">批量操作</label>
			<label index="cm.copyPasteActions">页面操作</label>
			<label index="cm.collapseBranch">折叠分支</label>
			<label index="cm.expandBranch">扩展分支</label>
			<label index="tree.defaultPageTitle">[默认标题]</label>
			<label index="tree.copyHint">按住Ctrl拷贝</label>
			<label index="tree.activeFilterMode">激活过滤模式</label>
			<label index="tree.dropToRemove">拖动这里删除</label>
			<label index="tree.dropZoneElementRemoved">点击这里撤销删除</label>
			<label index="tree.dropZoneElementRestored">页面恢复</label>
			<label index="tree.buttonNewNode">创建新页面</label>
			<label index="tree.buttonFilter">过滤页面</label>
			<label index="tree.searchTermInfo">输入搜索词</label>
			<label index="warning.install_password">安装密码默认为&quot;joh316&quot;,可在安装工具中更改</label>
			<label index="warning.backend_admin">后台默认用户”admin“和密码&quot;password&quot;仍旧未改变，%s编辑账户%s，删除或者更改用户名和密码。</label>
			<label index="warning.header">重要提示！</label>
			<label index="toolbarItems.shortcuts">快捷方式</label>
			<label index="toolbarItems.shortcut">快捷方式</label>
			<label index="toolbarItems.shortcutsGroup">快捷方式组</label>
			<label index="toolbarItems.shortcutsEdit">编辑快捷方式</label>
			<label index="toolbarItems.shortcutsDelete">删除快捷方式</label>
			<label index="toolbarItems.bookmarks">书签</label>
			<label index="toolbarItems.bookmark">书签</label>
			<label index="toolbarItems.bookmarksGroup">书签组</label>
			<label index="toolbarItems.bookmarksEdit">编辑书签</label>
			<label index="toolbarItems.bookmarksDelete">删除书签</label>
			<label index="toolbarItems.search">搜索</label>
			<label index="toolbarItems.workspace">工作空间</label>
			<label index="tabs.closeAll">关闭所有标签</label>
			<label index="tabs.closeOther">关闭其它标签</label>
			<label index="tabs.close">关闭标签</label>
			<label index="tabs.openInBrowserWindow">在浏览器窗口中打开</label>
			<label index="donateWindow.title">提示</label>
			<label index="donateWindow.button_disable">不再显示</label>
			<label index="donateWindow.button_postpone">随后再提醒</label>
			<label index="extension.not.installed">扩展&quot;%s&quot; 没有安装</label>
			<label index="link.to.dblist.correctly">请不要链接到这个页面，可使用t3lib_BEfunc::getListViewLink() 来产生链接</label>
			<label index="link.to.filefile.correctly">请不要链接到此页面</label>
			<label index="loadingIndicator">加载中...</label>
			<label index="csh_tooltip_loading">加载帮助中...</label>
		</languageKey>
	</data>
	<orig_hash type="array">
		<languageKey index="ch" type="array">
			<label index="labels.openInNewWindow" type="integer">43359464</label>
			<label index="labels.goBack" type="integer">36398395</label>
			<label index="labels.makeShortcut" type="integer">172171229</label>
			<label index="labels.lockedRecord" type="integer">198827351</label>
			<label index="labels.lockedRecord_content" type="integer">187177677</label>
			<label index="labels.showRecords" type="integer">159375536</label>
			<label index="labels.path" type="integer">180814866</label>
			<label index="labels.table" type="integer">85738935</label>
			<label index="labels.upOneLevel" type="integer">206589180</label>
			<label index="labels.enterSearchString" type="integer">109099181</label>
			<label index="labels.enterSearchLevels" type="integer">93282459</label>
			<label index="labels.noEditPermission" type="integer">199778334</label>
			<label index="labels.fieldsMissing" type="integer">244447562</label>
			<label index="labels.fieldsChanged" type="integer">196203045</label>
			<label index="labels.noRTEfound" type="integer">167686583</label>
			<label index="labels.showPalettes" type="integer">29229235</label>
			<label index="labels.showDescriptions" type="integer">52412881</label>
			<label index="labels.disableRTE" type="integer">236608630</label>
			<label index="labels._CONTROL_" type="integer">169186731</label>
			<label index="labels._PATH_" type="integer">180814866</label>
			<label index="labels._LOCALIZATION_" type="integer">57239651</label>
			<label index="labels.setFields" type="integer">263441433</label>
			<label index="labels.search" type="integer">20138052</label>
			<label index="labels.author" type="integer">152306160</label>
			<label index="labels.note" type="integer">264885215</label>
			<label index="labels.category" type="integer">90868382</label>
			<label index="labels.reload" type="integer">80857126</label>
			<label index="labels.csv" type="integer">27365093</label>
			<label index="labels.clear_cache" type="integer">256573092</label>
			<label index="labels.no_title" type="integer">184697729</label>
			<label index="labels.cancel" type="integer">245659783</label>
			<label index="labels.hidden" type="integer">128769925</label>
			<label index="labels.starttime" type="integer">174138022</label>
			<label index="labels.endtime" type="integer">141907953</label>
			<label index="labels.minutesHoursDaysYears" type="integer">180541581</label>
			<label index="labels.menu" type="integer">260506399</label>
			<label index="labels.showPage" type="integer">150194952</label>
			<label index="labels.showList" type="integer">112377765</label>
			<label index="labels.days" type="integer">72343236</label>
			<label index="labels.depth_0" type="integer">98872550</label>
			<label index="labels.depth_1" type="integer">200641290</label>
			<label index="labels.depth_2" type="integer">228799796</label>
			<label index="labels.depth_3" type="integer">195275893</label>
			<label index="labels.depth_4" type="integer">97262614</label>
			<label index="labels.depth_infi" type="integer">185655876</label>
			<label index="labels.allow" type="integer">73338807</label>
			<label index="labels.generalTab" type="double">14366585</label>
			<label index="labels.refresh" type="integer">218889859</label>
			<label index="labels.temporaryDBmount" type="integer">54643159</label>
			<label index="labels.refreshList" type="integer">267625353</label>
			<label index="labels.close" type="integer">222113377</label>
			<label index="labels.new" type="integer">38618522</label>
			<label index="labels.selected" type="integer">119647594</label>
			<label index="labels.items" type="integer">138035944</label>
			<label index="labels.remove_selected" type="integer">174131744</label>
			<label index="labels.move_to_top" type="integer">234987422</label>
			<label index="labels.move_up" type="integer">182650699</label>
			<label index="labels.move_down" type="integer">73063474</label>
			<label index="labels.move_to_bottom" type="integer">34443035</label>
			<label index="labels.browse_file" type="integer">252183313</label>
			<label index="labels.browse_db" type="double">3203407</label>
			<label index="labels.generalOptions" type="integer">70509926</label>
			<label index="labels.allTables" type="integer">64435182</label>
			<label index="labels.moreOptions" type="integer">220835237</label>
			<label index="labels.noMatchingValue" type="integer">216503775</label>
			<label index="labels.thumbmode_clip" type="integer">251068306</label>
			<label index="labels.copymode" type="integer">24481846</label>
			<label index="labels.clipNoEl" type="integer">213419996</label>
			<label index="labels.cliptabs" type="integer">219248137</label>
			<label index="labels.removeItem" type="integer">61210410</label>
			<label index="TYPO3_Element_Browser" type="integer">97099900</label>
			<label index="show_item.php.viewItem" type="integer">31794211</label>
			<label index="show_item.php.file" type="double">11696408</label>
			<label index="show_item.php.dimensions" type="integer">256394177</label>
			<label index="show_item.php.filesize" type="integer">116837234</label>
			<label index="show_item.php.ftp_area" type="integer">213910632</label>
			<label index="db_new.php.pagetitle" type="integer">153049580</label>
			<label index="db_new.php.after" type="integer">103981632</label>
			<label index="db_new.php.inside" type="integer">53858117</label>
			<label index="file_upload.php.pagetitle" type="integer">209578095</label>
			<label index="file_upload.php.submit" type="integer">209578095</label>
			<label index="file_upload.php.files" type="integer">73111091</label>
			<label index="file_rename.php.pagetitle" type="integer">151300144</label>
			<label index="file_rename.php.submit" type="integer">151300144</label>
			<label index="file_edit.php.pagetitle" type="integer">131916066</label>
			<label index="file_edit.php.submit" type="integer">211601612</label>
			<label index="file_edit.php.saveAndClose" type="integer">253538544</label>
			<label index="file_edit.php.coundNot" type="integer">155023303</label>
			<label index="file_newfolder.php.pagetitle" type="integer">37247196</label>
			<label index="file_newfolder.php.submit" type="integer">50275779</label>
			<label index="file_newfolder.php.folders" type="integer">130756931</label>
			<label index="file_newfolder.php.newfile_submit" type="integer">25278735</label>
			<label index="file_newfolder.php.newfile" type="integer">77930857</label>
			<label index="file_clipupload.php.warning_head" type="integer">159379252</label>
			<label index="file_clipupload.php.warning" type="integer">223829658</label>
			<label index="mess.redraw" type="integer">39712654</label>
			<label index="mess.delete" type="double">11983227</label>
			<label index="mess.deleteClip" type="integer">86922765</label>
			<label index="mess.refresh_login" type="integer">16856853</label>
			<label index="mess.noSelItemForEdit" type="integer">260947711</label>
			<label index="mess.onChangeAlert" type="integer">215006725</label>
			<label index="mess.move_into" type="integer">267594206</label>
			<label index="mess.move_after" type="integer">160860895</label>
			<label index="mess.copy_into" type="integer">231649592</label>
			<label index="mess.copy_after" type="integer">190775159</label>
			<label index="mess.copycb_into" type="integer">233579989</label>
			<label index="mess.copycb_after" type="integer">233968527</label>
			<label index="mess.movecb_into" type="integer">206869075</label>
			<label index="mess.movecb_after" type="integer">184153362</label>
			<label index="rm.menu" type="integer">41019420</label>
			<label index="rm.saveDoc" type="integer">34922005</label>
			<label index="rm.saveDocShow" type="integer">266586540</label>
			<label index="rm.saveCloseDoc" type="integer">43846535</label>
			<label index="rm.saveCloseAllDocs" type="integer">105962057</label>
			<label index="rm.saveNewDoc" type="integer">35091769</label>
			<label index="rm.closeDoc" type="integer">64132522</label>
			<label index="rm.closeAllDocs" type="integer">55835955</label>
			<label index="rm.clearCache_clearCache" type="integer">127667564</label>
			<label index="rm.clearCache_thisPage" type="integer">98872550</label>
			<label index="rm.clearCache_pages" type="integer">110711253</label>
			<label index="rm.clearCache_all" type="integer">251966384</label>
			<label index="rm.clearCache_allTypo3Conf" type="integer">166481656</label>
			<label index="rm.adminFunctions" type="integer">190550998</label>
			<label index="rm.edit" type="integer">131916066</label>
			<label index="rm.delete" type="integer">254438473</label>
			<label index="buttons.logout" type="double">3292644</label>
			<label index="buttons.clear" type="integer">230886336</label>
			<label index="buttons.clipboard" type="integer">37640827</label>
			<label index="cm.copy" type="integer">100361047</label>
			<label index="cm.cut" type="integer">246625500</label>
			<label index="cm.view" type="integer">77133724</label>
			<label index="cm.edit" type="integer">131916066</label>
			<label index="cm.new" type="double">3944062</label>
			<label index="cm.pasteinto" type="integer">46910930</label>
			<label index="cm.pasteafter" type="integer">48443221</label>
			<label index="cm.select" type="integer">235284002</label>
			<label index="cm.deselect" type="integer">155289095</label>
			<label index="cm.selectto" type="integer">188624416</label>
			<label index="cm.deselectto" type="integer">198679702</label>
			<label index="cm.delete" type="integer">254438473</label>
			<label index="cm.hide" type="integer">103439945</label>
			<label index="cm.unhide" type="integer">205596222</label>
			<label index="cm.upload" type="integer">194920219</label>
			<label index="cm.rename" type="integer">151300144</label>
			<label index="cm.open" type="integer">205255751</label>
			<label index="cm.save" type="integer">211601612</label>
			<label index="cm.unzip" type="integer">31401173</label>
			<label index="cm.info" type="integer">67476226</label>
			<label index="cm.createnew" type="integer">260012217</label>
			<label index="labels.clipInsert_file" type="integer">72963835</label>
			<label index="labels.clipInsert_db" type="integer">123875466</label>
			<label index="labels.setAllCheckboxes" type="integer">249015448</label>
			<label index="labels.expandAll" type="integer">218803276</label>
			<label index="ver.online" type="integer">141368811</label>
			<label index="ver.mgm" type="integer">75564445</label>
			<label index="ver.selVer" type="integer">141725286</label>
			<label index="rm.export" type="double">613023</label>
			<label index="buttons.selMenu_modules" type="integer">23513772</label>
			<label index="cm.tempMountPoint" type="double">10294929</label>
			<label index="labels.holdDownCTRL" type="integer">246729511</label>
			<label index="labels.revertSelection" type="integer">137669033</label>
			<label index="labels.changeInOrig" type="integer">97464470</label>
			<label index="ver.swap" type="integer">60665691</label>
			<label index="ver.swapPage" type="integer">206706262</label>
			<label index="labels.deny" type="integer">57158934</label>
			<label index="mess.refresh_login_username" type="integer">257964500</label>
			<label index="mess.refresh_login_password" type="integer">231098347</label>
			<label index="mess.refresh_login_button" type="integer">161344120</label>
			<label index="rm.translationSaveDoc" type="integer">135292122</label>
			<label index="rm.translationSaveDocClear" type="integer">10933576</label>
			<label index="rm.clearCacheMenu_all" type="integer">178010177</label>
			<label index="rm.clearCacheMenu_pages" type="integer">156459465</label>
			<label index="rm.clearCacheMenu_allTypo3Conf" type="integer">103495975</label>
			<label index="buttons.exit" type="integer">267339493</label>
			<label index="cm.copyPage_into" type="integer">121982700</label>
			<label index="cm.copyPage_after" type="integer">153137342</label>
			<label index="cm.movePage_into" type="integer">199131423</label>
			<label index="cm.movePage_after" type="integer">35697297</label>
			<label index="cm.copyFolder_into" type="integer">188539305</label>
			<label index="cm.moveFolder_into" type="integer">247629774</label>
			<label index="cm.createNewRelation" type="integer">191818165</label>
			<label index="toolbarItems.shortcuts" type="integer">43949454</label>
			<label index="toolbarItems.shortcut" type="integer">123085069</label>
			<label index="toolbarItems.shortcutsEdit" type="integer">52786352</label>
			<label index="toolbarItems.shortcutsDelete" type="integer">153062404</label>
			<label index="toolbarItems.search" type="integer">20138052</label>
			<label index="toolbarItems.workspace" type="integer">3809681</label>
			<label index="tabs.closeAll" type="integer">251797615</label>
			<label index="tabs.closeOther" type="integer">62899116</label>
			<label index="tabs.close" type="integer">51678512</label>
			<label index="donateWindow.title" type="integer">33294769</label>
			<label index="labels.lockedRecordUser" type="integer">223753993</label>
			<label index="labels.lockedRecordUser_content" type="integer">18938813</label>
			<label index="labels.user" type="integer">150585321</label>
			<label index="labels.beUser" type="integer">59315030</label>
			<label index="labels.feUser" type="integer">60089502</label>
			<label index="labels.unknownUser" type="integer">204028862</label>
			<label index="labels.resetFilter" type="integer">137474511</label>
			<label index="labels.expandTable" type="integer">105495039</label>
			<label index="labels.collapseTable" type="integer">99776408</label>
			<label index="labels.createNewPage" type="integer">61954051</label>
			<label index="labels.createNewRecord" type="integer">174229707</label>
			<label index="labels.createNewRecordRootLevel" type="integer">172023271</label>
			<label index="labels.editPage" type="integer">183842849</label>
			<label index="labels.editRecord" type="integer">141979566</label>
			<label index="labels.editRecordNoTitle" type="integer">101426271</label>
			<label index="labels.editRecordRootLevel" type="integer">107417425</label>
			<label index="labels.rootLevel" type="integer">50658212</label>
			<label index="labels.addnew" type="integer">251010995</label>
			<label index="labels.toggleall" type="integer">105039192</label>
			<label index="labels.move" type="integer">236525846</label>
			<label index="labels.generalOptions_more" type="integer">28006124</label>
			<label index="labels.checkAll" type="integer">192771126</label>
			<label index="labels.uncheckAll" type="integer">20591945</label>
			<label index="labels.new_section" type="integer">235813185</label>
			<label index="labels.count" type="integer">64016889</label>
			<label index="labels.findRecord" type="integer">31022019</label>
			<label index="labels.noRecordFound" type="integer">104635131</label>
			<label index="alttext.suggestSearching" type="integer">19152303</label>
			<label index="show_item.php.pixels" type="integer">205336413</label>
			<label index="show_item.php.files" type="integer">73111091</label>
			<label index="show_item.php.table" type="integer">82279689</label>
			<label index="file_newfolder.php.number_of_folders" type="integer">115219713</label>
			<label index="mess.refresh_login_refresh_button" type="integer">211599481</label>
			<label index="mess.refresh_logout_button" type="integer">3292644</label>
			<label index="mess.refresh_direct_logout_button" type="integer">60666823</label>
			<label index="mess.refresh_login_countdown" type="integer">143958536</label>
			<label index="mess.refresh_login_countdown_singular" type="integer">139100163</label>
			<label index="mess.refresh_login_logging_in" type="integer">76192403</label>
			<label index="mess.refresh_login_failed" type="integer">75909592</label>
			<label index="mess.refresh_login_failed_message" type="integer">100392131</label>
			<label index="mess.refresh_login_title" type="integer">239557783</label>
			<label index="mess.refresh_login_emptyPassword" type="integer">151805163</label>
			<label index="mess.please_wait" type="integer">150833642</label>
			<label index="mess.be_locked" type="integer">177753634</label>
			<label index="mess.login_about_to_expire" type="integer">65613066</label>
			<label index="mess.login_about_to_expire_title" type="integer">82252242</label>
			<label index="mess.login_expired" type="integer">78878748</label>
			<label index="warning.install_password" type="integer">38421646</label>
			<label index="warning.backend_admin" type="integer">92449882</label>
			<label index="labels.makeBookmark" type="integer">45160972</label>
			<label index="labels.automatic" type="integer">7049857</label>
			<label index="labels.enabled" type="integer">861095</label>
			<label index="labels.show" type="integer">77133724</label>
			<label index="cm.branchActions" type="integer">257504834</label>
			<label index="cm.copyPasteActions" type="integer">231283780</label>
			<label index="cm.collapseBranch" type="integer">222779750</label>
			<label index="cm.expandBranch" type="integer">14376827</label>
			<label index="tree.defaultPageTitle" type="integer">157086783</label>
			<label index="tree.copyHint" type="integer">23109650</label>
			<label index="tree.dropToRemove" type="integer">151163611</label>
			<label index="tree.dropZoneElementRemoved" type="integer">152478294</label>
			<label index="tree.dropZoneElementRestored" type="integer">109961606</label>
			<label index="tree.buttonNewNode" type="integer">203564147</label>
			<label index="toolbarItems.bookmarks" type="integer">128359787</label>
			<label index="toolbarItems.bookmark" type="integer">59439948</label>
			<label index="toolbarItems.bookmarksGroup" type="integer">28154119</label>
			<label index="toolbarItems.bookmarksEdit" type="integer">93197906</label>
			<label index="toolbarItems.bookmarksDelete" type="integer">240442651</label>
			<label index="tabs.openInBrowserWindow" type="integer">142944173</label>
			<label index="loadingIndicator" type="integer">113765784</label>
			<label index="csh_tooltip_loading" type="integer">133941053</label>
			<label index="tree.activeFilterMode" type="integer">72627589</label>
			<label index="tree.buttonFilter" type="integer">8245554</label>
			<label index="tree.searchTermInfo" type="integer">249385974</label>
			<label index="toolbarItems.shortcutsGroup" type="integer">128433730</label>
			<label index="file_upload.php.number_of_files" type="integer">14458467</label>
			<label index="show_item.php.cannotDisplayArchive" type="integer">4074166</label>
			<label index="donateWindow.button_disable" type="integer">179995460</label>
			<label index="donateWindow.button_postpone" type="integer">128250065</label>
			<label index="extension.not.installed" type="integer">249839602</label>
			<label index="link.to.dblist.correctly" type="integer">199750276</label>
			<label index="link.to.filefile.correctly" type="integer">2928116</label>
			<label index="warning.header" type="integer">267844976</label>
		</languageKey>
	</orig_hash>
	<orig_text type="array">
		<languageKey index="ch" type="array">
			<label index="labels.openInNewWindow">Open in new window</label>
			<label index="labels.goBack">Go back</label>
			<label index="labels.makeShortcut">Create a shortcut to this page?</label>
			<label index="labels.lockedRecord">The user '%s' began to edit this record %s ago.</label>
			<label index="labels.lockedRecord_content">The user '%s' began to edit content on this page %s ago.</label>
			<label index="labels.showRecords">Show records</label>
			<label index="labels.path">Path</label>
			<label index="labels.table">Table</label>
			<label index="labels.upOneLevel">Up one level</label>
			<label index="labels.enterSearchString">Search String:</label>
			<label index="labels.enterSearchLevels">This page|1 level down|2 levels down|3 levels down|4 levels down</label>
			<label index="labels.noEditPermission">Sorry, you didn't have proper permissions to perform this change.</label>
			<label index="labels.fieldsMissing">The fields marked with a yellow exclamation mark are not yet correctly filled in. Please complete them properly.</label>
			<label index="labels.fieldsChanged">There are unsaved changes in the form!
Do you want to continue WITHOUT saving?</label>
			<label index="labels.noRTEfound">Notice: This field can only be edited with a Rich Text Editor. No editor is currently available or enabled.</label>
			<label index="labels.showPalettes">Show secondary options (palettes)</label>
			<label index="labels.showDescriptions">Show field descriptions</label>
			<label index="labels.disableRTE">Disable Rich Text Editor (RTE)</label>
			<label index="labels._CONTROL_">Control</label>
			<label index="labels._PATH_">Path</label>
			<label index="labels._LOCALIZATION_">Localization</label>
			<label index="labels.setFields">Set fields</label>
			<label index="labels.search">Search</label>
			<label index="labels.author">Author:</label>
			<label index="labels.note">Note:</label>
			<label index="labels.category">Category:</label>
			<label index="labels.reload">Reload</label>
			<label index="labels.csv">Download CSV file</label>
			<label index="labels.clear_cache">Clear cache for this page</label>
			<label index="labels.no_title">No title</label>
			<label index="labels.cancel">Cancel</label>
			<label index="labels.hidden">Hidden</label>
			<label index="labels.starttime">Start</label>
			<label index="labels.endtime">End</label>
			<label index="labels.minutesHoursDaysYears">min| hrs| days| yrs</label>
			<label index="labels.menu">Menu:</label>
			<label index="labels.showPage">View webpage</label>
			<label index="labels.showList">Show record list</label>
			<label index="labels.days">days</label>
			<label index="labels.depth_0">This page</label>
			<label index="labels.depth_1">1 level</label>
			<label index="labels.depth_2">2 levels</label>
			<label index="labels.depth_3">3 levels</label>
			<label index="labels.depth_4">4 levels</label>
			<label index="labels.depth_infi">Infinite</label>
			<label index="labels.allow">Allow</label>
			<label index="labels.generalTab">General</label>
			<label index="labels.refresh">Reload the tree from server</label>
			<label index="labels.temporaryDBmount">Cancel temporary DB mount</label>
			<label index="labels.refreshList">Reload list from server</label>
			<label index="labels.close">Close</label>
			<label index="labels.new">NEW</label>
			<label index="labels.selected">Selected Items</label>
			<label index="labels.items">Available Items</label>
			<label index="labels.remove_selected">Remove selected items</label>
			<label index="labels.move_to_top">Move selected items to top</label>
			<label index="labels.move_up">Move selected items upwards</label>
			<label index="labels.move_down">Move selected items downwards</label>
			<label index="labels.move_to_bottom">Move selected items to bottom</label>
			<label index="labels.browse_file">Browse for files</label>
			<label index="labels.browse_db">Browse for records</label>
			<label index="labels.generalOptions">General options:</label>
			<label index="labels.allTables">[All tables]</label>
			<label index="labels.moreOptions">More options...</label>
			<label index="labels.noMatchingValue">INVALID VALUE (&quot;%s&quot;)</label>
			<label index="labels.thumbmode_clip">Show Thumbnails on ClipBoard</label>
			<label index="labels.copymode">Copy items instead of moving them</label>
			<label index="labels.clipNoEl">No elements</label>
			<label index="labels.cliptabs">Clipboard #</label>
			<label index="labels.removeItem">Remove item</label>
			<label index="TYPO3_Element_Browser">TYPO3 Element Browser</label>
			<label index="show_item.php.viewItem">View Item</label>
			<label index="show_item.php.file">File</label>
			<label index="show_item.php.dimensions">Dimensions</label>
			<label index="show_item.php.filesize">Size</label>
			<label index="show_item.php.ftp_area">FTP AREA</label>
			<label index="db_new.php.pagetitle">New record</label>
			<label index="db_new.php.after">after</label>
			<label index="db_new.php.inside">inside</label>
			<label index="file_upload.php.pagetitle">Upload files</label>
			<label index="file_upload.php.submit">Upload files</label>
			<label index="file_upload.php.files">files</label>
			<label index="file_rename.php.pagetitle">Rename</label>
			<label index="file_rename.php.submit">Rename</label>
			<label index="file_edit.php.pagetitle">Edit</label>
			<label index="file_edit.php.submit">Save</label>
			<label index="file_edit.php.saveAndClose">Save and Close</label>
			<label index="file_edit.php.coundNot">This filetype cannot be edited.&lt;br /&gt;The file must have an extension like:&lt;br /&gt;&lt;br /&gt; &lt;b&gt;%s&lt;/b&gt;</label>
			<label index="file_newfolder.php.pagetitle">New file or folder</label>
			<label index="file_newfolder.php.submit">Create folders</label>
			<label index="file_newfolder.php.folders">folders</label>
			<label index="file_newfolder.php.newfile_submit">Create file</label>
			<label index="file_newfolder.php.newfile">Create new textfile</label>
			<label index="file_clipupload.php.warning_head">Upload path error</label>
			<label index="file_clipupload.php.warning">No upload-folder is found. You should create a TEMP-folder (&quot;_temp_&quot;) in the root of one of your mounts first!</label>
			<label index="mess.redraw">Redrawing the page will discard the current data. Do you want to continue?</label>
			<label index="mess.delete">Are you sure you want to delete &quot;%s&quot;?</label>
			<label index="mess.deleteClip">Are you sure you want to delete ALL selected elements (%s) on the clipboard?</label>
			<label index="mess.refresh_login">Your login has probably expired.
Do you want to refresh it now?</label>
			<label index="mess.noSelItemForEdit">Please select one or more items in the list before you can edit.</label>
			<label index="mess.onChangeAlert">This change will affect which fields are available in the form.
Would you like to save now in order to refresh the display?</label>
			<label index="mess.move_into">Move &quot;%s&quot; into &quot;%s&quot;?</label>
			<label index="mess.move_after">Move &quot;%s&quot; to after &quot;%s&quot;?</label>
			<label index="mess.copy_into">Copy &quot;%s&quot; into &quot;%s&quot;?</label>
			<label index="mess.copy_after">Copy &quot;%s&quot; to after &quot;%s&quot;?</label>
			<label index="mess.copycb_into">Copy all elements (%s) from the clipboard into &quot;%s&quot;?</label>
			<label index="mess.copycb_after">Copy all elements (%s) from the clipboard to the position after &quot;%s&quot;?</label>
			<label index="mess.movecb_into">Move all elements (%s) from the clipboard into &quot;%s&quot;?</label>
			<label index="mess.movecb_after">Move all elements (%s) from the clipboard to the position after &quot;%s&quot;?</label>
			<label index="rm.menu">[menu]</label>
			<label index="rm.saveDoc">Save document</label>
			<label index="rm.saveDocShow">Save document and view page</label>
			<label index="rm.saveCloseDoc">Save and close document</label>
			<label index="rm.saveCloseAllDocs">Save and close all documents</label>
			<label index="rm.saveNewDoc">Save document and create a new one</label>
			<label index="rm.closeDoc">Close document</label>
			<label index="rm.closeAllDocs">Close all documents</label>
			<label index="rm.clearCache_clearCache">Clear cache</label>
			<label index="rm.clearCache_thisPage">This page</label>
			<label index="rm.clearCache_pages">Clear Page Cache</label>
			<label index="rm.clearCache_all">Clear FE cache</label>
			<label index="rm.clearCache_allTypo3Conf">Clear cache in typo3conf/</label>
			<label index="rm.adminFunctions">Admin functions</label>
			<label index="rm.edit">Edit</label>
			<label index="rm.delete">Delete</label>
			<label index="buttons.logout">Logout</label>
			<label index="buttons.clear">Clear</label>
			<label index="buttons.clipboard">Clipboard</label>
			<label index="cm.copy">Copy</label>
			<label index="cm.cut">Cut</label>
			<label index="cm.view">Show</label>
			<label index="cm.edit">Edit</label>
			<label index="cm.new">New</label>
			<label index="cm.pasteinto">Paste into</label>
			<label index="cm.pasteafter">Paste after</label>
			<label index="cm.select">Select</label>
			<label index="cm.deselect">Deselect</label>
			<label index="cm.selectto">Select to</label>
			<label index="cm.deselectto">Deselect to</label>
			<label index="cm.delete">Delete</label>
			<label index="cm.hide">Hide</label>
			<label index="cm.unhide">Unhide</label>
			<label index="cm.upload">Upload Files</label>
			<label index="cm.rename">Rename</label>
			<label index="cm.open">Open</label>
			<label index="cm.save">Save</label>
			<label index="cm.unzip">Unzip</label>
			<label index="cm.info">Info</label>
			<label index="cm.createnew">Create new</label>
			<label index="labels.clipInsert_file">Insert %s file(s) from the clipboard</label>
			<label index="labels.clipInsert_db">Insert %s record(s) from the clipboard</label>
			<label index="labels.setAllCheckboxes">Select All Checkboxes</label>
			<label index="labels.expandAll">Expand all</label>
			<label index="ver.online">ONLINE</label>
			<label index="ver.mgm">Version Management</label>
			<label index="ver.selVer">Select version:</label>
			<label index="rm.export">Export</label>
			<label index="buttons.selMenu_modules">MODULES</label>
			<label index="cm.tempMountPoint">Mount as treeroot</label>
			<label index="labels.holdDownCTRL">Important: Hold down the CTRL key while toggling elements in this list!</label>
			<label index="labels.revertSelection">Revert selection</label>
			<label index="labels.changeInOrig">Changed in original translation</label>
			<label index="ver.swap">Swap/Publish</label>
			<label index="ver.swapPage">Publish this version of the page including content</label>
			<label index="labels.deny">Deny</label>
			<label index="mess.refresh_login_username">Username</label>
			<label index="mess.refresh_login_password">Password</label>
			<label index="mess.refresh_login_button">Login</label>
			<label index="rm.translationSaveDoc">Translation finished, save and close</label>
			<label index="rm.translationSaveDocClear">Translation NOT finished, Save</label>
			<label index="rm.clearCacheMenu_all">Clear all caches</label>
			<label index="rm.clearCacheMenu_pages">Clear page content cache</label>
			<label index="rm.clearCacheMenu_allTypo3Conf">Clear configuration cache</label>
			<label index="buttons.exit">Exit</label>
			<label index="cm.copyPage_into">Copy page into</label>
			<label index="cm.copyPage_after">Copy page after</label>
			<label index="cm.movePage_into">Move page into</label>
			<label index="cm.movePage_after">Move page after</label>
			<label index="cm.copyFolder_into">Copy folder into</label>
			<label index="cm.moveFolder_into">Move folder into</label>
			<label index="cm.createNewRelation">Create new relation</label>
			<label index="toolbarItems.shortcuts">Shortcuts</label>
			<label index="toolbarItems.shortcut">Shortcut</label>
			<label index="toolbarItems.shortcutsEdit">Edit Shortcut</label>
			<label index="toolbarItems.shortcutsDelete">Delete Shortcut</label>
			<label index="toolbarItems.search">Search</label>
			<label index="toolbarItems.workspace">Workspace</label>
			<label index="tabs.closeAll">Close All Tabs</label>
			<label index="tabs.closeOther">Close Other Tabs</label>
			<label index="tabs.close">Close Tab</label>
			<label index="donateWindow.title">TYPO3 donation notice</label>
			<label index="labels.lockedRecordUser">The %s '%s' began to edit this record %s ago.</label>
			<label index="labels.lockedRecordUser_content">The %s '%s' began to edit content on this page %s ago.</label>
			<label index="labels.user">User</label>
			<label index="labels.beUser">BE-User</label>
			<label index="labels.feUser">FE-User</label>
			<label index="labels.unknownUser">-Unknown-</label>
			<label index="labels.resetFilter">Reset Filter</label>
			<label index="labels.expandTable">Expand table</label>
			<label index="labels.collapseTable">Collapse table</label>
			<label index="labels.createNewPage">Create new %s</label>
			<label index="labels.createNewRecord">Create new %s on page &quot;%s&quot;</label>
			<label index="labels.createNewRecordRootLevel">Create new %s on root level</label>
			<label index="labels.editPage">Edit %s &quot;%s&quot;</label>
			<label index="labels.editRecord">Edit %s &quot;%s&quot; on page &quot;%s&quot;</label>
			<label index="labels.editRecordNoTitle">Edit %s on page &quot;%s&quot;</label>
			<label index="labels.editRecordRootLevel">Edit %s &quot;%s&quot; on root level</label>
			<label index="labels.rootLevel">root level</label>
			<label index="labels.addnew">Add new</label>
			<label index="labels.toggleall">Toggle all</label>
			<label index="labels.move">Move this item</label>
			<label index="labels.generalOptions_more">General options (continued):</label>
			<label index="labels.checkAll">Check all</label>
			<label index="labels.uncheckAll">Uncheck all</label>
			<label index="labels.new_section">Create new:</label>
			<label index="labels.count">Quantity:</label>
			<label index="labels.findRecord">Find records</label>
			<label index="labels.noRecordFound">No record found</label>
			<label index="alttext.suggestSearching">Searching...</label>
			<label index="show_item.php.pixels">Pixels</label>
			<label index="show_item.php.files">files</label>
			<label index="show_item.php.table">Table:</label>
			<label index="file_newfolder.php.number_of_folders">Number of folders:</label>
			<label index="mess.refresh_login_refresh_button">Stay logged in!</label>
			<label index="mess.refresh_logout_button">Logout</label>
			<label index="mess.refresh_direct_logout_button">No, log out.</label>
			<label index="mess.refresh_login_countdown">{0} seconds</label>
			<label index="mess.refresh_login_countdown_singular">{0} second</label>
			<label index="mess.refresh_login_logging_in">Logging in...</label>
			<label index="mess.refresh_login_failed">Login failed</label>
			<label index="mess.refresh_login_failed_message">Password not correct.</label>
			<label index="mess.refresh_login_title">Refresh Login to TYPO3 (User: %s)</label>
			<label index="mess.refresh_login_emptyPassword">Empty password is not allowed!</label>
			<label index="mess.please_wait">Please wait ...</label>
			<label index="mess.be_locked">The TYPO3 backend is currently locked for maintenance. Leave this browser window open and the backend will automatically become available again once maintenance is complete.</label>
			<label index="mess.login_about_to_expire">Your TYPO3 login is about to expire. Please confirm that you want to stay logged in.</label>
			<label index="mess.login_about_to_expire_title">TYPO3 login expiration notice</label>
			<label index="mess.login_expired">Your TYPO3 login has expired. You need to login again if you want to continue. Otherwise you can close the current browser window.</label>
			<label index="warning.install_password">The Install Tool is still using the default password &quot;joh316&quot;. Update this within the %sAbout section%s of the Install Tool.</label>
			<label index="warning.backend_admin">The default backend user &quot;admin&quot; with password &quot;password&quot; is still present. %sEdit this account%s, either deleting it completely or changing the username and password.</label>
			<label index="labels.makeBookmark">Create a bookmark to this page</label>
			<label index="labels.automatic">Auto</label>
			<label index="labels.enabled">Enabled</label>
			<label index="labels.show">Show</label>
			<label index="cm.branchActions">Branch Actions</label>
			<label index="cm.copyPasteActions">Page Actions</label>
			<label index="cm.collapseBranch">Collapse Branch</label>
			<label index="cm.expandBranch">Expand Branch</label>
			<label index="tree.defaultPageTitle">[Default Title]</label>
			<label index="tree.copyHint">Press Ctrl to copy.</label>
			<label index="tree.dropToRemove">Drop here to delete</label>
			<label index="tree.dropZoneElementRemoved">Click here to undelete</label>
			<label index="tree.dropZoneElementRestored">Page restored</label>
			<label index="tree.buttonNewNode">Create new pages</label>
			<label index="toolbarItems.bookmarks">Bookmarks</label>
			<label index="toolbarItems.bookmark">Bookmark</label>
			<label index="toolbarItems.bookmarksGroup">Bookmark group</label>
			<label index="toolbarItems.bookmarksEdit">Edit bookmark</label>
			<label index="toolbarItems.bookmarksDelete">Delete bookmark</label>
			<label index="tabs.openInBrowserWindow">Open In Browser Window</label>
			<label index="loadingIndicator">Loading ...</label>
			<label index="csh_tooltip_loading">Loading help...</label>
			<label index="tree.activeFilterMode">Active Filtering Mode</label>
			<label index="tree.buttonFilter">Filter tree</label>
			<label index="tree.searchTermInfo">Enter search term</label>
			<label index="toolbarItems.shortcutsGroup">Shortcut Group</label>
			<label index="file_upload.php.number_of_files">Number of files:</label>
			<label index="show_item.php.cannotDisplayArchive">Sorry, TYPO3_CONF_VARS[BE][disable_exec_function] was set, so cannot display content of archive file.</label>
			<label index="donateWindow.button_disable">Never show again</label>
			<label index="donateWindow.button_postpone">Remind me later</label>
			<label index="extension.not.installed">Extension &quot;%s&quot; is not installed.</label>
			<label index="link.to.dblist.correctly">Please, do not link to this page. Use t3lib_BEfunc::getListViewLink() for link generation.</label>
			<label index="link.to.filefile.correctly">Please, do not link to this page.</label>
			<label index="warning.header">Important Notice!</label>
		</languageKey>
	</orig_text>
</T3locallangExt>