<?xml version="1.0" encoding="utf-8" standalone="yes" ?>
<T3locallangExt>
	<data type="array">
		<languageKey index="ch" type="array">
			<label index="pageTitle">页面标题:</label>
			<label index="path">路径:</label>
			<label index="user">用户:</label>
			<label index="group">组:</label>
			<label index="everybody">任何人:</label>
			<label index="thisUser">本用户:</label>
			<label index="mainGroup">主组:</label>
			<label index="live">[在线]</label>
			<label index="defaultDraft">[默认离线]</label>
			<label index="listUsersOnline">列出在线用户</label>
			<label index="backendUserAdministration">后台用户管理</label>
			<label index="filemounts">文件加载点</label>
			<label index="webmounts">网页加点</label>
			<label index="defaultUploadPath">默认上传路径</label>
			<label index="mainUserGroup">主用户组</label>
			<label index="memberOfGroups">用户组成员</label>
			<label index="pageTypesAccess">页面类型访问</label>
			<label index="selectTables">选择表</label>
			<label index="modifyTables">修改表</label>
			<label index="limitToLanguages">限制语言</label>
			<label index="workspacePermissions">工作空间权限</label>
			<label index="modules">模块</label>
			<label index="tsconfig">脚本配置</label>
			<label index="userInfo">用户信息</label>
			<label index="update">更新</label>
			<label index="newUser">创建新用户</label>
			<label index="usernames">用户名：</label>
			<label index="switchUserTo">转换用户到：</label>
			<label index="changeToMode">[更改模式]</label>
			<label index="result">结果</label>
			<label index="showInformation">显示信息</label>
			<label index="sureToDelete">你确认删除这个元素吗？</label>
			<label index="delete">删除(!)</label>
			<label index="timestamp">时间戳:</label>
			<label index="host">主机:</label>
			<label index="username">用户名:</label>
			<label index="whoIsOnline">谁在线</label>
		</languageKey>
	</data>
	<orig_hash type="array">
		<languageKey index="ch" type="array">
			<label index="pageTitle" type="integer">54388573</label>
			<label index="path" type="integer">266188054</label>
			<label index="user" type="integer">100638193</label>
			<label index="group" type="integer">27937892</label>
			<label index="everybody" type="integer">15655333</label>
			<label index="thisUser" type="integer">138389859</label>
			<label index="mainGroup" type="integer">177224527</label>
			<label index="delete" type="integer">95822415</label>
			<label index="timestamp" type="integer">172890</label>
			<label index="host" type="integer">142065542</label>
			<label index="username" type="integer">212632006</label>
			<label index="whoIsOnline" type="integer">238633576</label>
			<label index="listUsersOnline" type="integer">10753523</label>
			<label index="backendUserAdministration" type="integer">1134652</label>
			<label index="filemounts" type="integer">208929282</label>
			<label index="webmounts" type="integer">32273745</label>
			<label index="defaultUploadPath" type="integer">95580064</label>
			<label index="mainUserGroup" type="integer">154343976</label>
			<label index="memberOfGroups" type="integer">111843206</label>
			<label index="pageTypesAccess" type="integer">254976082</label>
			<label index="selectTables" type="integer">185925222</label>
			<label index="modifyTables" type="integer">145413787</label>
			<label index="limitToLanguages" type="integer">111675549</label>
			<label index="workspacePermissions" type="integer">220363531</label>
			<label index="userInfo" type="integer">213666707</label>
			<label index="usernames" type="integer">166454520</label>
			<label index="result" type="integer">149857824</label>
			<label index="showInformation" type="integer">123490643</label>
			<label index="sureToDelete" type="integer">134095347</label>
			<label index="modules" type="integer">200374977</label>
			<label index="tsconfig" type="integer">258585102</label>
			<label index="update" type="integer">6894342</label>
			<label index="live" type="integer">92369862</label>
			<label index="defaultDraft" type="integer">105965277</label>
			<label index="newUser" type="integer">63765912</label>
			<label index="switchUserTo" type="integer">266555586</label>
			<label index="changeToMode" type="integer">173120415</label>
		</languageKey>
	</orig_hash>
	<orig_text type="array">
		<languageKey index="ch" type="array">
			<label index="pageTitle">Page title:</label>
			<label index="path">Path:</label>
			<label index="user">User:</label>
			<label index="group">Group:</label>
			<label index="everybody">Everybody:</label>
			<label index="thisUser">This user:</label>
			<label index="mainGroup">Main group:</label>
			<label index="delete">Delete(!)</label>
			<label index="timestamp">Timestamp:</label>
			<label index="host">Host:</label>
			<label index="username">Username:</label>
			<label index="whoIsOnline">Who Is Online</label>
			<label index="listUsersOnline">List Users Online</label>
			<label index="backendUserAdministration">Backend User Administration</label>
			<label index="filemounts">Filemounts</label>
			<label index="webmounts">Webmounts</label>
			<label index="defaultUploadPath">Default upload path</label>
			<label index="mainUserGroup">Main user group</label>
			<label index="memberOfGroups">Member of groups</label>
			<label index="pageTypesAccess">Page types access</label>
			<label index="selectTables">Select tables</label>
			<label index="modifyTables">Modify tables</label>
			<label index="limitToLanguages">Limit to languages</label>
			<label index="workspacePermissions">Workspace permissions</label>
			<label index="userInfo">User Info</label>
			<label index="usernames">Usernames:</label>
			<label index="result">Result</label>
			<label index="showInformation">Show information</label>
			<label index="sureToDelete">Are you sure you want to delete this element?</label>
			<label index="modules">Modules</label>
			<label index="tsconfig">TSconfig</label>
			<label index="update">Update</label>
			<label index="live">[LIVE]</label>
			<label index="defaultDraft">[Default Draft]</label>
			<label index="newUser">Create new user</label>
			<label index="switchUserTo">Switch user to:</label>
			<label index="changeToMode">[change-to mode]</label>
		</languageKey>
	</orig_text>
</T3locallangExt>