<?xml version="1.0" encoding="utf-8" standalone="yes" ?>
<T3locallangExt>
	<data type="array">
		<languageKey index="ch" type="array">
			<label index="reg_user-sg">注册用户</label>
			<label index="reg_user-pl">注册用户</label>
			<label index="total_user-sg">用户</label>
			<label index="total_user-pl">用户</label>
			<label index="guest-sg">访客</label>
			<label index="guest-pl">访客</label>
			<label index="prd-pr-sg">是</label>
			<label index="prd-pr-pl">是</label>
			<label index="prd-vg-sg">是</label>
			<label index="prd-vg-pl">是</label>
			<label index="debug">运行时间: ###EXECUTION_TIME### 秒</label>
			<label index="ext-collapse">隐藏额外信息</label>
			<label index="ext-expand">显示额外信息</label>
			<label index="list-users">用户</label>
			<label index="list-moderators">版主</label>
			<label index="list-administrators">管理员</label>
			<label index="info-title">总览信息</label>
			<label index="info-currentTotal">现在，这里有 ###PRD### ###BESUCHER_TOTAL### ###BESUCHER_TOTAL_LABEL### 在线, 其中 ###BESUCHER_REG### ###BESUCHER_REG_LABEL### 和 ###BESUCHER_GAST### ###BESUCHER_GAST_LABEL###.</label>
			<label index="info-todayTotal">今天 ###BESUCHER_REG_HEUTE### ###BESUCHER_REG_HEUTE_LABEL### 和###BESUCHER_GAST_HEUTE### ###BESUCHER_GAST_HEUTE_LABEL### ###PRD### 已经在线.</label>
			<label index="info-currentlyOnline">现在在线</label>
			<label index="info-todayOnline">今日访客</label>
			<label index="info-stats">###SITENAME### 有 ###BENUTZER_TOTAL### 注册用户, ###THEMEN_TOTAL### 帖子和 ###ANTWORTEN_TOTAL### 回复. 平均每天 ###BEITRAEGE_SCHNITT### 帖子.</label>
		</languageKey>
	</data>
	<orig_hash type="array">
		<languageKey index="ch" type="array">
			<label index="reg_user-sg" type="integer">28114546</label>
			<label index="reg_user-pl" type="integer">69286198</label>
			<label index="total_user-sg" type="integer">249633979</label>
			<label index="total_user-pl" type="integer">163341762</label>
			<label index="guest-sg" type="integer">8708148</label>
			<label index="guest-pl" type="integer">154561063</label>
			<label index="prd-pr-sg" type="integer">170546458</label>
			<label index="prd-pr-pl" type="integer">67198620</label>
			<label index="prd-vg-sg" type="integer">175616857</label>
			<label index="prd-vg-pl" type="integer">45094617</label>
			<label index="ext-collapse" type="integer">8702630</label>
			<label index="ext-expand" type="integer">143107693</label>
			<label index="list-users" type="integer">150585321</label>
			<label index="list-moderators" type="integer">212228712</label>
			<label index="list-administrators" type="integer">129481765</label>
			<label index="info-title" type="integer">258364145</label>
			<label index="info-currentlyOnline" type="integer">86311464</label>
			<label index="info-todayOnline" type="integer">237835611</label>
			<label index="info-stats" type="integer">106492359</label>
			<label index="debug" type="integer">242340692</label>
			<label index="info-currentTotal" type="integer">72479673</label>
			<label index="info-todayTotal" type="integer">133565982</label>
		</languageKey>
	</orig_hash>
	<orig_text type="array">
		<languageKey index="ch" type="array">
			<label index="reg_user-sg">registered user</label>
			<label index="reg_user-pl">registered users</label>
			<label index="total_user-sg">user</label>
			<label index="total_user-pl">users</label>
			<label index="guest-sg">guest</label>
			<label index="guest-pl">guests</label>
			<label index="prd-pr-sg">is</label>
			<label index="prd-pr-pl">are</label>
			<label index="prd-vg-sg">was</label>
			<label index="prd-vg-pl">were</label>
			<label index="ext-collapse">Hide additional information</label>
			<label index="ext-expand">Show additional information</label>
			<label index="list-users">User</label>
			<label index="list-moderators">Moderator</label>
			<label index="list-administrators">Administrator</label>
			<label index="info-title">Portal information</label>
			<label index="info-currentlyOnline">Now online</label>
			<label index="info-todayOnline">Today's visitors</label>
			<label index="info-stats">###SITENAME### has ###BENUTZER_TOTAL### registered user, ###THEMEN_TOTAL### topics and ###ANTWORTEN_TOTAL### answers. On average ###BEITRAEGE_SCHNITT### posts are written per day.</label>
			<label index="debug">Duration time: ###EXECUTION_TIME### seconds</label>
			<label index="info-currentTotal">At the moment there ###PRD### ###BESUCHER_TOTAL### ###BESUCHER_TOTAL_LABEL### online, thereof ###BESUCHER_REG### ###BESUCHER_REG_LABEL### and ###BESUCHER_GAST### ###BESUCHER_GAST_LABEL###.</label>
			<label index="info-todayTotal">Today  ###BESUCHER_REG_HEUTE### ###BESUCHER_REG_HEUTE_LABEL### and ###BESUCHER_GAST_HEUTE### ###BESUCHER_GAST_HEUTE_LABEL### ###PRD### already online.</label>
		</languageKey>
	</orig_text>
</T3locallangExt>