<?xml version="1.0"?>
<entity_cms>
  <cms id="Delivery">
    <meta_title>配送</meta_title>
    <meta_description>配送协议</meta_description>
    <meta_keywords>配送, 协议, 运输, 包装</meta_keywords>
    <content>&lt;h2&gt;配送及退货&lt;/h2&gt;&lt;h3&gt;配送&lt;/h3&gt;&lt;p&gt;一般在付款完成后的2天内完成包装并配送。通常使用顺丰、申通等快递，如果你需要使用其他指定快递，可能需要其他额外的费用，所以请在购买前先进行沟通。&lt;/p&gt;&lt;p&gt;费用包含运输费和包装费。运输费一般根据配送重量计算。如果两个商品运往同一地点，我们建议一起配送。配送风险将由您个人承担。&lt;br /&gt;&lt;br /&gt;包装为普通包装盒&lt;/p&gt;</content>
    <link_rewrite>delivery</link_rewrite>
  </cms>
  <cms id="Legal_Notice">
    <meta_title>Legal Notice</meta_title>
    <meta_description>Legal notice</meta_description>
    <meta_keywords>notice, legal, credits</meta_keywords>
    <content>&lt;h2&gt;Legal&lt;/h2&gt;&lt;h3&gt;Credits&lt;/h3&gt;&lt;p&gt;Concept and production:&lt;/p&gt;&lt;p&gt;This Web site was created using &lt;a href="http://www.milebiz.com"&gt;MileBiz&lt;/a&gt;&amp;trade; open-source software.&lt;/p&gt;</content>
    <link_rewrite>legal-notice</link_rewrite>
  </cms>
  <cms id="Terms_and_conditions_of_use">
    <meta_title>条款与细则</meta_title>
    <meta_description>条款与细则</meta_description>
    <meta_keywords>条款, 细则, 使用, 购买</meta_keywords>
    <content>&lt;h2&gt;使用条款及细则&lt;/h2&gt;&lt;h3&gt;条款1&lt;/h3&gt;&lt;p&gt;这是使用条款1的内容&lt;/p&gt;&#xD;
&lt;h3&gt;条款2&lt;/h3&gt;&lt;p&gt;这是使用条款2的内容&lt;/p&gt;&#xD;
&lt;h3&gt;条款3&lt;/h3&gt;&lt;p&gt;这是使用条款3的内容&lt;/p&gt;</content>
    <link_rewrite>terms-and-conditions-of-use</link_rewrite>
  </cms>
  <cms id="About_us">
    <meta_title>关于我们</meta_title>
    <meta_description>关于我们</meta_description>
    <meta_keywords>关于我们, 信息</meta_keywords>
    <content>&lt;h2&gt;关于我们&lt;/h2&gt;&#xD;
&lt;h3&gt;我们的公司&lt;/h3&gt;&lt;p&gt;我们的公司&lt;/p&gt;&#xD;
&lt;h3&gt;我们的团队&lt;/h3&gt;&lt;p&gt;我们的团队&lt;/p&gt;&#xD;
&lt;h3&gt;其他信息&lt;/h3&gt;&lt;p&gt;其他信息&lt;/p&gt;</content>
    <link_rewrite>about-us</link_rewrite>
  </cms>
  <cms id="Secure_payment">
    <meta_title>安全支付</meta_title>
    <meta_description>安全支付</meta_description>
    <meta_keywords>安全支付, ssl, visa, mastercard, 支付宝</meta_keywords>
    <content>&lt;h2&gt;安全支付&lt;/h2&gt;&#xD;
&lt;h3&gt;安全支付&lt;/h3&gt;&lt;p&gt;使用SSL&lt;/p&gt;&#xD;
&lt;h3&gt;使用银联 或 支付宝&lt;/h3&gt;&lt;p&gt;关于这项服务&lt;/p&gt;</content>
    <link_rewrite>secure-payment</link_rewrite>
  </cms>
</entity_cms>
